{
"skeleton": { "hash": "YzffeXlH6Tw", "spine": "4.1.24", "x": -376.11, "y": -343.05, "width": 903.29, "height": 845 },
"bones": [
	{ "name": "root" },
	{ "name": "bone", "parent": "root", "x": 1.95, "y": 26.03 },
	{ "name": "bady", "parent": "bone", "x": -7.85, "y": 18.18 },
	{ "name": "face", "parent": "bone", "x": -13.85, "y": 2.91 },
	{ "name": "L_foot", "parent": "bone", "length": 127.03, "rotation": -136.91, "x": -32.24, "y": -269.07 },
	{ "name": "L_hand", "parent": "bone", "length": 40.37, "rotation": -170.13, "x": -249.4, "y": 30.52 },
	{ "name": "R_foot", "parent": "bone", "length": 121.5, "rotation": -12.32, "x": 139.69, "y": -213.21 },
	{ "name": "R_hand", "parent": "bone", "length": 49.12, "rotation": 34.61, "x": 232.15, "y": 49.09 },
	{ "name": "R_hand2", "parent": "R_hand", "length": 48.89, "rotation": -8.34, "x": 50.88, "y": 1.55 },
	{ "name": "R_hand3", "parent": "R_hand2", "length": 43.08, "rotation": -18.67, "x": 48.89 },
	{ "name": "R_hand4", "parent": "R_hand3", "length": 41.35, "rotation": -30.28, "x": 43.08 },
	{ "name": "R_hand5", "parent": "R_hand4", "length": 45.8, "rotation": -15.76, "x": 41.35 },
	{ "name": "R_hand6", "parent": "R_hand5", "length": 39.65, "rotation": -16.5, "x": 46.15, "y": -0.45 },
	{ "name": "R_hand7", "parent": "R_hand6", "length": 35.85, "rotation": -14.61, "x": 40.12, "y": -0.33 },
	{ "name": "L_hand2", "parent": "L_hand", "length": 33.57, "rotation": -21.75, "x": 39.8, "y": 0.1 },
	{ "name": "L_hand3", "parent": "L_hand2", "length": 34.38, "rotation": -43.36, "x": 33.01, "y": -0.12 },
	{ "name": "L_hand4", "parent": "L_hand3", "length": 36.86, "rotation": -24.85, "x": 33.76, "y": 1.13 },
	{ "name": "L_hand5", "parent": "L_hand4", "length": 40.96, "rotation": -23.74, "x": 38.19, "y": 0.94 },
	{ "name": "L_hand6", "parent": "L_hand5", "length": 30.09, "rotation": -6.33, "x": 40.96 },
	{ "name": "L_hand7", "parent": "L_hand6", "length": 46.17, "rotation": -4.16, "x": 30.09 },
	{ "name": "bady2", "parent": "bady", "length": 142.42, "rotation": 47.34, "x": 72.27, "y": 286.26 }
],
"slots": [
	{ "name": "L_foot", "bone": "L_foot", "attachment": "watermelon/L_foot" },
	{ "name": "R_foot", "bone": "R_foot", "attachment": "watermelon/R_foot" },
	{ "name": "R_hand", "bone": "R_hand", "attachment": "watermelon/R_hand" },
	{ "name": "bady", "bone": "bady", "attachment": "watermelon/bady" },
	{ "name": "face", "bone": "face", "attachment": "watermelon/face" },
	{ "name": "L_hand", "bone": "L_hand", "attachment": "watermelon/L_hand" },
	{ "name": "watermelon/face_1", "bone": "face" },
	{ "name": "watermelon/face_2", "bone": "face" },
	{ "name": "watermelon/face_3", "bone": "face" },
	{ "name": "watermelon/face_4", "bone": "face" }
],
"skins": [
	{
		"name": "skin0",
		"attachments": {
			"bady": {
				"watermelon/bady": {
					"name": "skin0/bady",
					"type": "mesh",
					"uvs": [ 0.67078, 0, 0.73821, 0.01477, 0.81771, 0.04559, 0.87201, 0.07743, 0.91427, 0.10787, 0.95812, 0.15074, 0.97365, 0.17258, 0.97482, 0.20088, 0.97033, 0.22374, 0.94903, 0.2491, 0.89563, 0.27602, 0.86267, 0.27624, 0.80284, 0.22792, 0.79649, 0.22404, 0.75499, 0.19764, 0.74227, 0.20866, 0.72411, 0.22178, 0.70731, 0.2446, 0.75716, 0.26431, 0.82772, 0.3084, 0.87047, 0.34435, 0.91762, 0.3881, 0.95303, 0.43139, 0.98332, 0.48492, 0.9968, 0.56911, 0.99957, 0.64186, 0.99219, 0.71069, 0.97472, 0.77031, 0.93837, 0.81567, 0.89983, 0.84899, 0.85029, 0.88409, 0.81474, 0.90564, 0.75593, 0.93418, 0.71565, 0.95043, 0.63925, 0.97368, 0.59539, 0.9829, 0.47847, 0.99859, 0.39138, 0.99923, 0.32276, 0.98973, 0.25711, 0.96951, 0.21656, 0.95108, 0.17375, 0.92732, 0.12053, 0.88814, 0.06705, 0.83835, 0.0329, 0.78493, 0.0141, 0.74552, 0.00156, 0.69233, 0.00153, 0.62464, 0.00677, 0.57523, 0.02817, 0.51756, 0.06749, 0.45267, 0.12015, 0.40068, 0.16376, 0.36482, 0.21451, 0.32599, 0.25065, 0.29856, 0.30965, 0.26447, 0.3643, 0.24051, 0.41004, 0.22884, 0.47386, 0.21811, 0.53353, 0.2136, 0.54507, 0.20232, 0.57187, 0.16511, 0.61271, 0.13453, 0.59024, 0.12487, 0.52075, 0.10378, 0.56311, 0.04874, 0.60454, 0.01615, 0.63666, 0.00648, 0.66468, 0 ],
					"triangles": [ 11, 12, 10, 10, 12, 9, 8, 9, 7, 60, 61, 17, 17, 61, 16, 16, 61, 62, 7, 9, 12, 5, 7, 12, 12, 13, 4, 13, 14, 4, 7, 5, 6, 12, 4, 5, 16, 62, 15, 15, 62, 14, 62, 1, 14, 1, 62, 0, 0, 62, 67, 67, 68, 0, 14, 3, 4, 14, 2, 3, 14, 1, 2, 63, 66, 62, 62, 66, 67, 64, 65, 63, 63, 65, 66, 40, 36, 37, 35, 36, 40, 37, 39, 40, 34, 35, 40, 34, 51, 33, 37, 38, 39, 41, 42, 34, 32, 33, 51, 32, 24, 31, 49, 51, 34, 52, 32, 51, 24, 32, 52, 30, 31, 24, 52, 53, 24, 53, 54, 19, 54, 55, 19, 19, 17, 18, 19, 55, 17, 58, 17, 55, 55, 56, 57, 55, 57, 58, 58, 59, 17, 59, 60, 17, 49, 34, 42, 49, 50, 51, 40, 41, 34, 29, 30, 24, 20, 53, 19, 28, 29, 24, 53, 20, 24, 42, 46, 49, 27, 28, 24, 20, 21, 24, 42, 44, 46, 42, 43, 44, 25, 26, 27, 21, 22, 24, 44, 45, 46, 48, 49, 47, 25, 27, 24, 23, 24, 22, 49, 46, 47 ],
					"vertices": [ 1, 20, 146.56, 93.98, 1, 1, 20, 165.57, 56.48, 1, 1, 20, 180.35, 5.24, 1, 1, 20, 184.31, -35.42, 1, 1, 20, 184.16, -70.03, 1, 1, 20, 177.59, -111.87, 1, 1, 20, 171.47, -130.18, 1, 1, 20, 153.25, -142.21, 1, 1, 20, 140.42, -145.61, 1, 1, 20, 122.23, -144.51, 1, 1, 20, 107.37, -136.47, 1, 1, 20, 93.84, -122.04, 1, 1, 20, 97.02, -70.3, 1, 1, 20, 96.65, -65.46, 1, 1, 20, 94.8, -33.3, 1, 1, 20, 82.08, -29.03, 1, 2, 2, 116.39, 290.21, 0.0386, 20, 32.8, -29.78, 0.9614, 2, 2, 106.32, 272.54, 0.84154, 20, 12.98, -34.34, 0.15846, 1, 2, 149.44, 248.63, 1, 1, 2, 191.78, 214.5, 1, 1, 2, 217.11, 189.27, 1, 1, 2, 245.4, 155.4, 1, 1, 2, 267.93, 122.22, 1, 1, 2, 286.11, 80.79, 1, 1, 2, 298.08, 17.24, 1, 1, 2, 299.74, -39.06, 1, 1, 2, 295.31, -92.34, 1, 1, 2, 284.83, -138.49, 1, 1, 2, 263.02, -173.6, 1, 1, 2, 239.9, -199.39, 1, 1, 2, 210.17, -226.55, 1, 1, 2, 188.84, -243.23, 1, 1, 2, 153.56, -265.32, 1, 1, 2, 129.39, -277.9, 1, 1, 2, 83.55, -295.9, 1, 1, 2, 57.23, -303.03, 1, 1, 2, -12.92, -315.17, 1, 1, 2, -65.17, -315.67, 1, 1, 2, -106.34, -308.32, 1, 1, 2, -145.73, -292.67, 1, 1, 2, -170.07, -278.4, 1, 1, 2, -195.75, -260.02, 1, 1, 2, -227.68, -229.69, 1, 1, 2, -259.77, -191.15, 1, 1, 2, -280.26, -149.8, 1, 1, 2, -291.54, -119.3, 1, 1, 2, -299.06, -78.13, 1, 1, 2, -299.08, -25.74, 1, 1, 2, -294.06, 9.69, 1, 1, 2, -281.22, 54.33, 1, 1, 2, -255.29, 104.09, 1, 1, 2, -223.7, 144.32, 1, 1, 2, -196.71, 173.47, 1, 1, 2, -166.26, 203.52, 1, 1, 2, -145.83, 220.98, 1, 1, 2, -110.44, 247.37, 1, 1, 2, -78.37, 266.49, 1, 1, 2, -50.93, 275.53, 1, 1, 2, -16.36, 284.17, 1, 2, 2, 32.66, 285.62, 0.69129, 20, -27.31, 28.69, 0.30871, 2, 2, 38.23, 296.39, 0.1849, 20, -15.61, 31.9, 0.8151, 1, 20, 16.46, 39.59, 1, 1, 20, 81.15, 36.83, 1, 1, 20, 77.51, 51.81, 1, 1, 20, 61.26, 93.53, 1, 1, 20, 75.88, 107.02, 1, 1, 20, 111.28, 105.83, 1, 1, 20, 129.44, 102.2, 1, 1, 20, 144.09, 96.67, 1 ],
					"hull": 69
				}
			},
			"face": {
				"watermelon/face": { "name": "skin0/face", "width": 366, "height": 354 }
			},
			"L_foot": {
				"watermelon/L_foot": { "name": "skin0/L_foot", "x": 59.93, "y": 9.01, "rotation": 136.91, "width": 158, "height": 105 }
			},
			"L_hand": {
				"watermelon/L_hand": {
					"name": "skin0/L_hand",
					"type": "mesh",
					"uvs": [ 0.82453, 0, 0.92466, 0, 0.97082, 0.01932, 0.99426, 0.04951, 0.99442, 0.12489, 0.9727, 0.16797, 0.94946, 0.19135, 0.94168, 0.20498, 0.97612, 0.25237, 0.97812, 0.28831, 0.94955, 0.33616, 0.88153, 0.38231, 0.78954, 0.40864, 0.67307, 0.41937, 0.44881, 0.41991, 0.30702, 0.55169, 0.25848, 0.60601, 0.21247, 0.67468, 0.20877, 0.68273, 0.18944, 0.73618, 0.1874, 0.76582, 0.20423, 0.8178, 0.21984, 0.84415, 0.23339, 0.85844, 0.27227, 0.8853, 0.28718, 0.88945, 0.3389, 0.89988, 0.43068, 0.90708, 0.50108, 0.91284, 0.62208, 0.91284, 0.6539, 0.92358, 0.67899, 0.95309, 0.66493, 0.97845, 0.62721, 1, 0.41116, 1, 0.30011, 0.99058, 0.19462, 0.97207, 0.08641, 0.91227, 0.04549, 0.85414, 0.02848, 0.80832, 0.02331, 0.78309, 0.02297, 0.72819, 0.02586, 0.72422, 0.03507, 0.6741, 0.09885, 0.56847, 0.21566, 0.4491, 0.23389, 0.4325, 0.12282, 0.43234, 0.04677, 0.39042, 0.02518, 0.36734, 0.01576, 0.34428, 0.01786, 0.2965, 0.05849, 0.27386, 0.08187, 0.26761, 0.17982, 0.26763, 0.15124, 0.20504, 0.15206, 0.16431, 0.18771, 0.12446, 0.25957, 0.09794, 0.31718, 0.09536, 0.37738, 0.11211, 0.42791, 0.15914, 0.59379, 0.06461, 0.71152, 0.02372, 0.7764, 0.00876 ],
					"triangles": [ 4, 1, 3, 3, 1, 2, 1, 4, 0, 5, 6, 4, 4, 6, 0, 56, 61, 55, 61, 54, 55, 58, 59, 60, 57, 58, 60, 57, 60, 61, 57, 61, 56, 10, 7, 8, 10, 8, 9, 52, 50, 51, 53, 49, 50, 53, 50, 52, 54, 49, 53, 0, 7, 64, 6, 7, 0, 11, 7, 10, 7, 63, 64, 7, 62, 63, 7, 61, 62, 61, 7, 13, 48, 49, 54, 11, 12, 7, 12, 13, 7, 14, 54, 61, 13, 14, 61, 46, 47, 48, 48, 54, 46, 14, 46, 54, 15, 46, 14, 45, 46, 15, 44, 45, 15, 16, 44, 15, 17, 43, 44, 16, 17, 44, 18, 43, 17, 19, 43, 18, 42, 43, 19, 19, 41, 42, 20, 41, 19, 40, 41, 20, 39, 40, 20, 39, 20, 21, 38, 39, 21, 38, 21, 22, 37, 38, 22, 37, 22, 23, 24, 36, 37, 24, 37, 23, 36, 24, 25, 35, 25, 26, 36, 25, 35, 35, 26, 34, 32, 30, 31, 34, 26, 27, 34, 27, 28, 32, 33, 29, 32, 29, 30, 28, 29, 33, 34, 28, 33 ],
					"vertices": [ 1, 19, 184.94, 1.81, 1, 1, 19, 194.04, -12.69, 1, 1, 19, 193.16, -22.56, 1, 1, 19, 187.37, -30.93, 1, 1, 19, 167.59, -43.38, 1, 1, 19, 154.3, -47.33, 1, 1, 19, 146.05, -47.81, 1, 1, 19, 141.76, -48.93, 1, 1, 19, 132.45, -61.73, 1, 1, 19, 123.2, -67.94, 1, 1, 19, 108.03, -71.69, 1, 1, 19, 89.74, -69.44, 1, 1, 19, 74.46, -60.46, 1, 1, 19, 61.05, -45.36, 1, 1, 19, 40.53, -12.97, 1, 2, 18, 22.12, -13.6, 0.86363, 19, -6.96, -14.14, 0.13637, 3, 16, 71.49, -29.49, 0.00316, 17, 42.73, -14.45, 0.33654, 18, 3.35, -14.17, 0.6603, 3, 16, 50.51, -20.84, 0.25883, 17, 20.04, -14.98, 0.73715, 18, -19.14, -17.2, 0.00402, 4, 15, 68.89, -37.32, 4.4E-4, 16, 48.04, -20.12, 0.3589, 17, 17.49, -15.31, 0.64056, 18, -21.64, -17.81, 1.1E-4, 3, 15, 55.62, -26.85, 0.04879, 16, 31.6, -16.2, 0.94235, 17, 0.87, -18.35, 0.00886, 2, 15, 47.59, -22.38, 0.21275, 16, 22.43, -15.52, 0.78725, 3, 14, 44.12, -34.86, 0.00196, 15, 31.92, -17.63, 0.93036, 16, 6.22, -17.8, 0.06768, 2, 14, 38.85, -28.06, 0.03553, 15, 23.43, -16.31, 0.96447, 2, 14, 35.18, -24.67, 0.09676, 15, 18.43, -16.36, 0.90324, 3, 5, 56.99, -27.29, 0.00554, 14, 26.12, -19.07, 0.46343, 15, 8, -18.51, 0.53104, 3, 5, 54.48, -25.91, 0.01668, 14, 23.28, -18.72, 0.59444, 15, 5.69, -20.2, 0.38888, 3, 5, 45.76, -22.36, 0.13715, 14, 13.86, -18.65, 0.75613, 15, -1.2, -26.62, 0.10672, 3, 5, 30.16, -19.56, 0.70969, 14, -1.67, -21.83, 0.28801, 15, -10.3, -39.59, 0.0023, 2, 5, 18.19, -17.34, 0.96029, 14, -13.6, -24.2, 0.03971, 1, 5, -2.48, -16.59, 1, 1, 5, -7.8, -13.06, 1, 1, 5, -11.75, -3.77, 1, 1, 5, -9.07, 4, 1, 1, 5, -2.38, 10.44, 1, 2, 5, 34.54, 9.1, 0.92621, 14, -8.22, 6.42, 0.07379, 1, 14, 10.64, 10.06, 1, 2, 14, 29.56, 10.73, 0.90817, 15, -9.95, 5.52, 0.09183, 2, 15, 14.96, 13.6, 0.7624, 16, -22.3, 3.42, 0.2376, 1, 16, -4.03, 9.74, 1, 2, 16, 10.27, 12.13, 0.97668, 17, -30.07, -1, 0.02332, 2, 16, 18.12, 12.72, 0.90275, 17, -23.12, 2.7, 0.09725, 2, 16, 35.13, 12.15, 0.22643, 17, -7.32, 9.03, 0.77357, 2, 16, 36.34, 11.61, 0.1655, 17, -6, 9.02, 0.8345, 1, 17, 9.03, 13.29, 1, 2, 17, 43.49, 15.22, 0.37571, 18, 0.83, 15.4, 0.62429, 2, 18, 42.89, 15.11, 0.05844, 19, 11.67, 15.99, 0.94156, 2, 18, 48.89, 14.76, 0.00386, 19, 17.68, 16.09, 0.99614, 1, 19, 7.63, 32.2, 1, 1, 19, 11.73, 50.13, 1, 1, 19, 15.82, 57.05, 1, 1, 19, 21.02, 62.22, 1, 1, 19, 33.76, 69.79, 1, 1, 19, 43.4, 67.64, 1, 1, 19, 47.16, 65.28, 1, 1, 19, 56.06, 51.09, 1, 1, 19, 69.9, 65.54, 1, 1, 19, 80.67, 72.13, 1, 1, 19, 94.37, 73.54, 1, 1, 19, 107.87, 67.5, 1, 1, 19, 113.78, 59.58, 1, 1, 19, 114.86, 48.1, 1, 1, 19, 107.1, 33.03, 1, 1, 19, 147, 24.59, 1, 1, 19, 168.44, 14.27, 1, 1, 19, 178.26, 7.34, 1 ],
					"hull": 65
				}
			},
			"R_foot": {
				"watermelon/R_foot": { "name": "skin0/R_foot", "x": 68.87, "y": -15.54, "rotation": 12.32, "width": 145, "height": 80 }
			},
			"R_hand": {
				"watermelon/R_hand": {
					"name": "skin0/R_hand",
					"type": "mesh",
					"uvs": [ 0.36771, 0, 0.40469, 0, 0.46227, 0, 0.55066, 0.04934, 0.60174, 0.10062, 0.63898, 0.138, 0.69367, 0.21574, 0.73793, 0.29405, 0.77702, 0.3632, 0.80215, 0.43657, 0.82744, 0.51037, 0.84009, 0.5645, 0.86367, 0.53736, 0.88292, 0.53803, 0.91932, 0.60525, 0.93561, 0.61976, 0.99691, 0.61965, 0.99667, 0.70761, 0.98657, 0.74265, 0.9669, 0.7771, 0.94313, 0.8054, 0.97317, 0.85123, 0.97305, 0.91162, 0.96643, 0.93639, 0.93819, 0.98411, 0.91694, 0.99427, 0.87813, 0.99429, 0.84452, 0.96484, 0.80064, 0.8892, 0.78054, 0.89155, 0.73892, 0.9313, 0.69285, 1, 0.65861, 1, 0.64135, 0.97025, 0.62882, 0.92721, 0.62711, 0.85482, 0.63906, 0.77449, 0.6573, 0.71192, 0.69177, 0.62941, 0.74157, 0.59289, 0.72037, 0.52743, 0.68979, 0.45341, 0.67342, 0.41742, 0.62681, 0.33657, 0.57363, 0.27051, 0.54053, 0.23416, 0.50025, 0.19916, 0.4528, 0.17225, 0.41288, 0.15817, 0.3615, 0.158, 0.32795, 0.16961, 0.26466, 0.21337, 0.18738, 0.29484, 0.12307, 0.37281, 0.06539, 0.45528, 0.03291, 0.45911, 0.01709, 0.44537, 0, 0.41546, 0, 0.32713, 0.07122, 0.22667, 0.13988, 0.14803, 0.20837, 0.06957, 0.28896, 0.01528, 0.32362, 0 ],
					"triangles": [ 40, 9, 10, 39, 40, 10, 39, 10, 11, 17, 15, 16, 18, 15, 17, 19, 15, 18, 20, 15, 19, 28, 39, 11, 29, 38, 39, 29, 37, 38, 29, 36, 37, 36, 30, 35, 11, 12, 13, 11, 13, 14, 20, 28, 11, 28, 29, 39, 22, 20, 21, 30, 34, 35, 36, 29, 30, 23, 20, 22, 28, 20, 27, 11, 14, 20, 15, 20, 14, 27, 20, 26, 31, 33, 34, 23, 24, 20, 24, 25, 20, 25, 26, 20, 31, 32, 33, 34, 30, 31, 42, 43, 7, 41, 42, 7, 8, 41, 7, 40, 41, 8, 9, 40, 8, 45, 3, 4, 44, 45, 4, 44, 4, 5, 43, 44, 5, 43, 5, 6, 43, 6, 7, 47, 48, 2, 47, 2, 3, 46, 47, 3, 45, 46, 3, 49, 63, 0, 48, 1, 2, 49, 0, 1, 48, 49, 1, 50, 63, 49, 62, 63, 50, 51, 61, 62, 51, 62, 50, 51, 52, 60, 51, 60, 61, 59, 60, 52, 53, 59, 52, 58, 59, 53, 56, 57, 58, 58, 54, 56, 53, 54, 58, 55, 56, 54 ],
					"vertices": [ 1, 9, 23.4, 9, 1, 1, 9, 34.25, 7.55, 1, 2, 9, 51.15, 5.3, 0.02752, 10, 4.3, 8.64, 0.97248, 2, 10, 31.69, 10.94, 0.99344, 11, -12.27, 7.91, 0.00656, 2, 10, 49.02, 8.68, 0.09126, 11, 5.03, 10.44, 0.90874, 1, 11, 17.64, 12.29, 1, 2, 11, 38.58, 11.94, 0.96512, 12, -10.78, 9.72, 0.03488, 2, 11, 57.17, 9.59, 0.04965, 12, 7.71, 12.76, 0.95035, 2, 12, 24.04, 15.43, 0.998, 13, -19.53, 11.19, 0.002, 2, 12, 38.58, 14.32, 0.6558, 13, -5.18, 13.78, 0.3442, 2, 12, 53.21, 13.19, 0.03765, 13, 9.26, 16.39, 0.96235, 1, 13, 19.24, 16.66, 1, 1, 13, 17.33, 24.82, 1, 1, 13, 19.43, 30.12, 1, 1, 13, 33.96, 36.2, 1, 1, 13, 37.97, 39.85, 1, 1, 13, 44.29, 56.86, 1, 1, 13, 58.36, 51.54, 1, 1, 13, 62.93, 46.64, 1, 1, 13, 66.42, 39.13, 1, 1, 13, 68.49, 30.84, 1, 1, 13, 78.94, 36.44, 1, 1, 13, 88.61, 32.8, 1, 1, 13, 91.89, 29.48, 1, 1, 13, 96.62, 18.8, 1, 1, 13, 96.05, 12.3, 1, 1, 13, 92.04, 1.53, 1, 1, 13, 83.84, -6.03, 1, 2, 11, 134.97, -58.58, 0, 13, 67.19, -13.68, 1, 2, 11, 130.56, -62.6, 0, 13, 65.48, -19.39, 1, 2, 11, 125.14, -75.58, 0, 13, 67.55, -33.31, 1, 2, 11, 121.76, -93.26, 0, 13, 73.79, -50.19, 1, 2, 11, 113.82, -99.56, 0, 13, 70.25, -59.69, 1, 2, 11, 106.66, -98.75, 0, 13, 63.7, -62.7, 1, 2, 11, 99.18, -95.29, 0, 13, 55.51, -63.6, 1, 2, 11, 91.08, -85.91, 0, 13, 43.73, -59.75, 1, 2, 11, 85.32, -72.95, 0, 13, 32.1, -51.64, 1, 2, 11, 82.89, -61.21, 0, 13, 23.96, -42.84, 1, 2, 11, 82.11, -43.82, 0, 13, 14.3, -28.35, 1, 3, 11, 89.78, -29.77, 0, 12, 50.16, -15.72, 0.02417, 13, 13.6, -12.36, 0.97583, 3, 11, 77.9, -24.9, 0, 12, 37.39, -14.43, 0.57091, 13, 0.92, -14.33, 0.42909, 3, 11, 62.95, -20.61, 0.00537, 12, 21.83, -14.56, 0.98682, 13, -14.1, -18.39, 0.00781, 2, 11, 55.33, -18.8, 0.0796, 12, 14.01, -14.99, 0.9204, 2, 11, 35.92, -16.55, 0.84739, 12, -5.23, -18.35, 0.15261, 2, 10, 52.55, -21.33, 0.04957, 11, 16.57, -17.49, 0.95043, 2, 10, 41.11, -19.37, 0.37524, 11, 5.03, -18.71, 0.62476, 3, 9, 57.79, -29.95, 0.01116, 10, 27.8, -18.45, 0.851, 11, -8.03, -21.43, 0.13783, 3, 9, 44.48, -23.53, 0.20183, 10, 13.07, -19.62, 0.79408, 11, -21.89, -26.56, 0.00409, 2, 9, 33.08, -19.58, 0.65256, 10, 1.24, -21.95, 0.34744, 3, 8, 60.34, -22.39, 0.04177, 9, 18.01, -17.54, 0.92359, 10, -12.81, -27.79, 0.03464, 4, 7, 98.03, -25.35, 1.2E-4, 8, 50.56, -19.77, 0.28866, 9, 7.91, -18.2, 0.70957, 10, -21.2, -33.45, 0.00164, 3, 7, 78.36, -20.87, 0.04922, 8, 30.44, -18.19, 0.88837, 9, -11.65, -23.14, 0.06241, 2, 7, 51.62, -19.34, 0.8002, 8, 3.77, -20.56, 0.1998, 1, 7, 28.38, -19.5, 1, 1, 7, 6.32, -21.41, 1, 1, 7, -1.96, -16.49, 1, 1, 7, -4.48, -11.89, 1, 1, 7, -5.74, -4.81, 1, 1, 7, 2.84, 7.62, 1, 2, 7, 29.95, 9.79, 0.97182, 8, -21.91, 5.11, 0.02818, 1, 8, 2.27, 8.17, 1, 1, 8, 26.38, 11.23, 1, 2, 8, 51.88, 9, 0.36491, 9, -0.05, 9.49, 0.63509, 1, 9, 10.47, 10.72, 1 ],
					"hull": 64
				}
			},
			"watermelon/face_1": {
				"watermelon/face_1": { "name": "skin0/face_1", "x": 0.5, "width": 437, "height": 336 }
			},
			"watermelon/face_2": {
				"watermelon/face_2": { "name": "skin0/face_2", "x": -155.93, "y": 43.32, "width": 495, "height": 408 }
			},
			"watermelon/face_3": {
				"watermelon/face_3": { "name": "skin0/face_3", "x": -36.44, "y": 31.34, "rotation": -10.61, "width": 408, "height": 476 }
			},
			"watermelon/face_4": {
				"watermelon/face_4": { "name": "skin0/face_4", "x": -92.09, "y": 13.07, "rotation": -25.86, "width": 660, "height": 535 }
			}
		}
	},
	{
		"name": "skin1",
		"attachments": {
			"bady": {
				"watermelon/bady": { "name": "skin1/bady", "type": "linkedmesh", "skin": "skin0", "parent": "watermelon/bady" }
			},
			"face": {
				"watermelon/face": { "name": "skin1/face", "width": 366, "height": 354 }
			},
			"L_foot": {
				"watermelon/L_foot": { "name": "skin1/L_foot", "x": 59.93, "y": 9.01, "rotation": 136.91, "width": 158, "height": 105 }
			},
			"L_hand": {
				"watermelon/L_hand": { "name": "skin1/L_hand", "type": "linkedmesh", "skin": "skin0", "parent": "watermelon/L_hand" }
			},
			"R_foot": {
				"watermelon/R_foot": { "name": "skin1/R_foot", "x": 68.87, "y": -15.54, "rotation": 12.32, "width": 145, "height": 80 }
			},
			"R_hand": {
				"watermelon/R_hand": { "name": "skin1/R_hand", "type": "linkedmesh", "skin": "skin0", "parent": "watermelon/R_hand" }
			},
			"watermelon/face_1": {
				"watermelon/face_1": { "name": "skin1/face_1", "x": 0.5, "width": 437, "height": 336 }
			},
			"watermelon/face_2": {
				"watermelon/face_2": { "name": "skin1/face_2", "x": -155.93, "y": 43.32, "width": 495, "height": 408 }
			},
			"watermelon/face_3": {
				"watermelon/face_3": { "name": "skin1/face_3", "x": -36.44, "y": 31.34, "rotation": -10.61, "width": 408, "height": 476 }
			},
			"watermelon/face_4": {
				"watermelon/face_4": { "name": "skin1/face_4", "x": -92.09, "y": 13.07, "rotation": -25.86, "width": 660, "height": 535 }
			}
		}
	},
	{
		"name": "skin2",
		"attachments": {
			"bady": {
				"watermelon/bady": { "name": "skin2/bady", "type": "linkedmesh", "skin": "skin0", "parent": "watermelon/bady" }
			},
			"face": {
				"watermelon/face": { "name": "skin2/face", "width": 366, "height": 354 }
			},
			"L_foot": {
				"watermelon/L_foot": { "name": "skin2/L_foot", "x": 59.93, "y": 9.01, "rotation": 136.91, "width": 158, "height": 105 }
			},
			"L_hand": {
				"watermelon/L_hand": { "name": "skin2/L_hand", "type": "linkedmesh", "skin": "skin0", "parent": "watermelon/L_hand" }
			},
			"R_foot": {
				"watermelon/R_foot": { "name": "skin2/R_foot", "x": 68.87, "y": -15.54, "rotation": 12.32, "width": 145, "height": 80 }
			},
			"R_hand": {
				"watermelon/R_hand": { "name": "skin2/R_hand", "type": "linkedmesh", "skin": "skin0", "parent": "watermelon/R_hand" }
			},
			"watermelon/face_1": {
				"watermelon/face_1": { "name": "skin2/face_1", "x": 0.5, "width": 437, "height": 336 }
			},
			"watermelon/face_2": {
				"watermelon/face_2": { "name": "skin2/face_2", "x": -155.93, "y": 43.32, "width": 495, "height": 408 }
			},
			"watermelon/face_3": {
				"watermelon/face_3": { "name": "skin2/face_3", "x": -36.44, "y": 31.34, "rotation": -10.61, "width": 408, "height": 476 }
			},
			"watermelon/face_4": {
				"watermelon/face_4": { "name": "skin2/face_4", "x": -92.09, "y": 13.07, "rotation": -25.86, "width": 660, "height": 535 }
			}
		}
	},
	{
		"name": "skin3",
		"attachments": {
			"bady": {
				"watermelon/bady": { "name": "skin3/bady", "type": "linkedmesh", "skin": "skin0", "parent": "watermelon/bady" }
			},
			"face": {
				"watermelon/face": { "name": "skin3/face", "width": 366, "height": 354 }
			},
			"L_foot": {
				"watermelon/L_foot": { "name": "skin3/L_foot", "x": 59.93, "y": 9.01, "rotation": 136.91, "width": 158, "height": 105 }
			},
			"L_hand": {
				"watermelon/L_hand": { "name": "skin3/L_hand", "type": "linkedmesh", "skin": "skin0", "parent": "watermelon/L_hand" }
			},
			"R_foot": {
				"watermelon/R_foot": { "name": "skin3/R_foot", "x": 68.87, "y": -15.54, "rotation": 12.32, "width": 145, "height": 80 }
			},
			"R_hand": {
				"watermelon/R_hand": { "name": "skin3/R_hand", "type": "linkedmesh", "skin": "skin0", "parent": "watermelon/R_hand" }
			},
			"watermelon/face_1": {
				"watermelon/face_1": { "name": "skin3/face_1", "x": 0.5, "width": 437, "height": 336 }
			},
			"watermelon/face_2": {
				"watermelon/face_2": { "name": "skin3/face_2", "x": -155.93, "y": 43.32, "width": 495, "height": 408 }
			},
			"watermelon/face_3": {
				"watermelon/face_3": { "name": "skin3/face_3", "x": -36.44, "y": 31.34, "rotation": -10.61, "width": 408, "height": 476 }
			},
			"watermelon/face_4": {
				"watermelon/face_4": { "name": "skin3/face_4", "x": -92.09, "y": 13.07, "rotation": -25.86, "width": 660, "height": 535 }
			}
		}
	},
	{
		"name": "skin4",
		"attachments": {
			"bady": {
				"watermelon/bady": { "name": "skin4/bady", "type": "linkedmesh", "skin": "skin0", "parent": "watermelon/bady" }
			},
			"face": {
				"watermelon/face": { "name": "skin4/face", "width": 366, "height": 354 }
			},
			"L_foot": {
				"watermelon/L_foot": { "name": "skin4/L_foot", "x": 59.93, "y": 9.01, "rotation": 136.91, "width": 158, "height": 105 }
			},
			"L_hand": {
				"watermelon/L_hand": { "name": "skin4/L_hand", "type": "linkedmesh", "skin": "skin0", "parent": "watermelon/L_hand" }
			},
			"R_foot": {
				"watermelon/R_foot": { "name": "skin4/R_foot", "x": 68.87, "y": -15.54, "rotation": 12.32, "width": 145, "height": 80 }
			},
			"R_hand": {
				"watermelon/R_hand": { "name": "skin4/R_hand", "type": "linkedmesh", "skin": "skin0", "parent": "watermelon/R_hand" }
			},
			"watermelon/face_1": {
				"watermelon/face_1": { "name": "skin4/face_1", "x": 0.5, "width": 437, "height": 336 }
			},
			"watermelon/face_2": {
				"watermelon/face_2": { "name": "skin4/face_2", "x": -155.93, "y": 43.32, "width": 495, "height": 408 }
			},
			"watermelon/face_3": {
				"watermelon/face_3": { "name": "skin4/face_3", "x": -36.44, "y": 31.34, "rotation": -10.61, "width": 408, "height": 476 }
			},
			"watermelon/face_4": {
				"watermelon/face_4": { "name": "skin4/face_4", "x": -92.09, "y": 13.07, "rotation": -25.86, "width": 660, "height": 535 }
			}
		}
	},
	{
		"name": "skin5",
		"attachments": {
			"bady": {
				"watermelon/bady": { "name": "skin5/bady", "type": "linkedmesh", "skin": "skin0", "parent": "watermelon/bady" }
			},
			"face": {
				"watermelon/face": { "name": "skin5/face", "width": 366, "height": 354 }
			},
			"L_foot": {
				"watermelon/L_foot": { "name": "skin5/L_foot", "x": 59.93, "y": 9.01, "rotation": 136.91, "width": 158, "height": 105 }
			},
			"L_hand": {
				"watermelon/L_hand": { "name": "skin5/L_hand", "type": "linkedmesh", "skin": "skin0", "parent": "watermelon/L_hand" }
			},
			"R_foot": {
				"watermelon/R_foot": { "name": "skin5/R_foot", "x": 68.87, "y": -15.54, "rotation": 12.32, "width": 145, "height": 80 }
			},
			"R_hand": {
				"watermelon/R_hand": { "name": "skin5/R_hand", "type": "linkedmesh", "skin": "skin0", "parent": "watermelon/R_hand" }
			},
			"watermelon/face_1": {
				"watermelon/face_1": { "name": "skin5/face_1", "x": 0.5, "width": 437, "height": 336 }
			},
			"watermelon/face_2": {
				"watermelon/face_2": { "name": "skin5/face_2", "x": -155.93, "y": 43.32, "width": 495, "height": 408 }
			},
			"watermelon/face_3": {
				"watermelon/face_3": { "name": "skin5/face_3", "x": -36.44, "y": 31.34, "rotation": -10.61, "width": 408, "height": 476 }
			},
			"watermelon/face_4": {
				"watermelon/face_4": { "name": "skin5/face_4", "x": -92.09, "y": 13.07, "rotation": -25.86, "width": 660, "height": 535 }
			}
		}
	},
	{
		"name": "skin6",
		"attachments": {
			"bady": {
				"watermelon/bady": { "name": "skin6/bady", "type": "linkedmesh", "skin": "skin0", "parent": "watermelon/bady" }
			},
			"face": {
				"watermelon/face": { "name": "skin6/face", "width": 366, "height": 354 }
			},
			"L_foot": {
				"watermelon/L_foot": { "name": "skin6/L_foot", "x": 59.93, "y": 9.01, "rotation": 136.91, "width": 158, "height": 105 }
			},
			"L_hand": {
				"watermelon/L_hand": { "name": "skin6/L_hand", "type": "linkedmesh", "skin": "skin0", "parent": "watermelon/L_hand" }
			},
			"R_foot": {
				"watermelon/R_foot": { "name": "skin6/R_foot", "x": 68.87, "y": -15.54, "rotation": 12.32, "width": 145, "height": 80 }
			},
			"R_hand": {
				"watermelon/R_hand": { "name": "skin6/R_hand", "type": "linkedmesh", "skin": "skin0", "parent": "watermelon/R_hand" }
			},
			"watermelon/face_1": {
				"watermelon/face_1": { "name": "skin6/face_1", "x": 0.5, "width": 437, "height": 336 }
			},
			"watermelon/face_2": {
				"watermelon/face_2": { "name": "skin6/face_2", "x": -155.93, "y": 43.32, "width": 495, "height": 408 }
			},
			"watermelon/face_3": {
				"watermelon/face_3": { "name": "skin6/face_3", "x": -36.44, "y": 31.34, "rotation": -10.61, "width": 408, "height": 476 }
			},
			"watermelon/face_4": {
				"watermelon/face_4": { "name": "skin6/face_4", "x": -92.09, "y": 13.07, "rotation": -25.86, "width": 660, "height": 535 }
			}
		}
	},
	{
		"name": "skin7",
		"attachments": {
			"bady": {
				"watermelon/bady": { "name": "skin7/bady", "type": "linkedmesh", "skin": "skin0", "parent": "watermelon/bady" }
			},
			"face": {
				"watermelon/face": { "name": "skin7/face", "width": 366, "height": 354 }
			},
			"L_foot": {
				"watermelon/L_foot": { "name": "skin7/L_foot", "x": 59.93, "y": 9.01, "rotation": 136.91, "width": 158, "height": 105 }
			},
			"L_hand": {
				"watermelon/L_hand": { "name": "skin7/L_hand", "type": "linkedmesh", "skin": "skin0", "parent": "watermelon/L_hand" }
			},
			"R_foot": {
				"watermelon/R_foot": { "name": "skin7/R_foot", "x": 68.87, "y": -15.54, "rotation": 12.32, "width": 145, "height": 80 }
			},
			"R_hand": {
				"watermelon/R_hand": { "name": "skin7/R_hand", "type": "linkedmesh", "skin": "skin0", "parent": "watermelon/R_hand" }
			},
			"watermelon/face_1": {
				"watermelon/face_1": { "name": "skin7/face_1", "x": 0.5, "width": 437, "height": 336 }
			},
			"watermelon/face_2": {
				"watermelon/face_2": { "name": "skin7/face_2", "x": -155.93, "y": 43.32, "width": 495, "height": 408 }
			},
			"watermelon/face_3": {
				"watermelon/face_3": { "name": "skin7/face_3", "x": -36.44, "y": 31.34, "rotation": -10.61, "width": 408, "height": 476 }
			},
			"watermelon/face_4": {
				"watermelon/face_4": { "name": "skin7/face_4", "x": -92.09, "y": 13.07, "rotation": -25.86, "width": 660, "height": 535 }
			}
		}
	}
],
"animations": {
	"attack": {
		"slots": {
			"face": {
				"attachment": [
					{ "name": "watermelon/face" }
				]
			},
			"watermelon/face_1": {
				"attachment": [
					{}
				]
			},
			"watermelon/face_2": {
				"attachment": [
					{}
				]
			},
			"watermelon/face_3": {
				"attachment": [
					{}
				]
			},
			"watermelon/face_4": {
				"attachment": [
					{}
				]
			}
		},
		"bones": {
			"L_hand": {
				"rotate": [
					{
						"value": -5.67,
						"curve": [ 0.056, -5.67, 0.111, -2.87 ]
					},
					{
						"time": 0.1667,
						"value": -2.4,
						"curve": [ 0.333, -0.98, 0.5, 0 ]
					},
					{ "time": 0.6667 }
				],
				"translate": [
					{ "curve": "stepped" },
					{ "time": 0.6667 }
				],
				"scale": [
					{ "curve": "stepped" },
					{ "time": 0.6667 }
				],
				"shear": [
					{ "curve": "stepped" },
					{ "time": 0.6667 }
				]
			},
			"L_hand7": {
				"rotate": [
					{
						"value": 17.92,
						"curve": [ 0.056, 17.92, 0.111, -2.4 ]
					},
					{
						"time": 0.1667,
						"value": -2.4,
						"curve": [ 0.333, -2.4, 0.5, 0 ]
					},
					{ "time": 0.6667 }
				],
				"translate": [
					{ "curve": "stepped" },
					{ "time": 0.6667 }
				],
				"scale": [
					{ "curve": "stepped" },
					{ "time": 0.6667 }
				],
				"shear": [
					{ "curve": "stepped" },
					{ "time": 0.6667 }
				]
			},
			"L_hand6": {
				"rotate": [
					{
						"value": 17.92,
						"curve": [ 0.056, 17.92, 0.111, -2.4 ]
					},
					{
						"time": 0.1667,
						"value": -2.4,
						"curve": [ 0.333, -2.4, 0.5, 0 ]
					},
					{ "time": 0.6667 }
				],
				"translate": [
					{ "curve": "stepped" },
					{ "time": 0.6667 }
				],
				"scale": [
					{ "curve": "stepped" },
					{ "time": 0.6667 }
				],
				"shear": [
					{ "curve": "stepped" },
					{ "time": 0.6667 }
				]
			},
			"L_hand5": {
				"rotate": [
					{
						"value": 17.92,
						"curve": [ 0.056, 17.92, 0.111, -2.4 ]
					},
					{
						"time": 0.1667,
						"value": -2.4,
						"curve": [ 0.333, -2.4, 0.5, 0 ]
					},
					{ "time": 0.6667 }
				],
				"translate": [
					{ "curve": "stepped" },
					{ "time": 0.6667 }
				],
				"scale": [
					{ "curve": "stepped" },
					{ "time": 0.6667 }
				],
				"shear": [
					{ "curve": "stepped" },
					{ "time": 0.6667 }
				]
			},
			"L_hand4": {
				"rotate": [
					{
						"value": 17.92,
						"curve": [ 0.056, 17.92, 0.111, -2.4 ]
					},
					{
						"time": 0.1667,
						"value": -2.4,
						"curve": [ 0.333, -2.4, 0.5, 0 ]
					},
					{ "time": 0.6667 }
				],
				"translate": [
					{ "curve": "stepped" },
					{ "time": 0.6667 }
				],
				"scale": [
					{ "curve": "stepped" },
					{ "time": 0.6667 }
				],
				"shear": [
					{ "curve": "stepped" },
					{ "time": 0.6667 }
				]
			},
			"L_hand3": {
				"rotate": [
					{
						"value": 17.92,
						"curve": [ 0.056, 17.92, 0.111, -2.4 ]
					},
					{
						"time": 0.1667,
						"value": -2.4,
						"curve": [ 0.333, -2.4, 0.5, 0 ]
					},
					{ "time": 0.6667 }
				],
				"translate": [
					{ "curve": "stepped" },
					{ "time": 0.6667 }
				],
				"scale": [
					{ "curve": "stepped" },
					{ "time": 0.6667 }
				],
				"shear": [
					{ "curve": "stepped" },
					{ "time": 0.6667 }
				]
			},
			"L_hand2": {
				"rotate": [
					{
						"value": 17.92,
						"curve": [ 0.056, 17.92, 0.111, -2.4 ]
					},
					{
						"time": 0.1667,
						"value": -2.4,
						"curve": [ 0.333, -2.4, 0.5, 0 ]
					},
					{ "time": 0.6667 }
				],
				"translate": [
					{ "curve": "stepped" },
					{ "time": 0.6667 }
				],
				"scale": [
					{ "curve": "stepped" },
					{ "time": 0.6667 }
				],
				"shear": [
					{ "curve": "stepped" },
					{ "time": 0.6667 }
				]
			},
			"root": {
				"rotate": [
					{ "curve": "stepped" },
					{ "time": 0.6667 }
				],
				"translate": [
					{ "curve": "stepped" },
					{ "time": 0.6667 }
				],
				"scale": [
					{ "curve": "stepped" },
					{ "time": 0.6667 }
				],
				"shear": [
					{ "curve": "stepped" },
					{ "time": 0.6667 }
				]
			},
			"bone": {
				"rotate": [
					{
						"value": 10.37,
						"curve": [ 0.056, 10.37, 0.111, -8.09 ]
					},
					{
						"time": 0.1667,
						"value": -8.09,
						"curve": [ 0.333, -8.09, 0.5, 0 ]
					},
					{ "time": 0.6667 }
				],
				"translate": [
					{
						"time": 0.0667,
						"curve": [ 0.1, 0, 0.134, 65.37, 0.1, 0, 0.134, -9.29 ]
					},
					{
						"time": 0.1667,
						"x": 65.37,
						"y": -9.29,
						"curve": [ 0.268, 65.37, 0.367, 0, 0.268, -9.29, 0.367, 0 ]
					},
					{ "time": 0.4667, "curve": "stepped" },
					{ "time": 0.6667 }
				],
				"scale": [
					{ "curve": "stepped" },
					{ "time": 0.6667 }
				],
				"shear": [
					{ "curve": "stepped" },
					{ "time": 0.6667 }
				]
			},
			"bady": {
				"rotate": [
					{ "curve": "stepped" },
					{ "time": 0.6667 }
				],
				"translate": [
					{
						"curve": [ 0.056, 0, 0.113, 19.16, 0.056, 0, 0.113, 0 ]
					},
					{
						"time": 0.1667,
						"x": 19.16,
						"curve": [ 0.335, 19.16, 0.501, 0, 0.335, 0, 0.501, 0 ]
					},
					{ "time": 0.6667 }
				],
				"scale": [
					{
						"curve": [ 0.056, 1, 0.113, 0.916, 0.056, 1, 0.113, 1 ]
					},
					{
						"time": 0.1667,
						"x": 0.916,
						"curve": [ 0.279, 0.916, 0.39, 0.953, 0.279, 1, 0.39, 0.918 ]
					},
					{
						"time": 0.5,
						"x": 0.978,
						"y": 0.918,
						"curve": [ 0.556, 0.99, 0.611, 1, 0.556, 0.918, 0.611, 1 ]
					},
					{ "time": 0.6667 }
				],
				"shear": [
					{ "curve": "stepped" },
					{ "time": 0.6667 }
				]
			},
			"face": {
				"rotate": [
					{ "curve": "stepped" },
					{ "time": 0.6667 }
				],
				"translate": [
					{
						"curve": [ 0.167, 0, 0.113, 23.18, 0.167, 0, 0.113, 0 ]
					},
					{
						"time": 0.1667,
						"x": 23.18,
						"curve": [ 0.335, 23.18, 0.501, 0, 0.335, 0, 0.501, 0 ]
					},
					{ "time": 0.6667 }
				],
				"scale": [
					{ "curve": "stepped" },
					{ "time": 0.6667 }
				],
				"shear": [
					{ "curve": "stepped" },
					{ "time": 0.6667 }
				]
			},
			"L_foot": {
				"rotate": [
					{
						"value": -13.05,
						"curve": [ 0.056, -13.05, 0.111, -17.09 ]
					},
					{
						"time": 0.1667,
						"value": -17.09,
						"curve": [ 0.333, -17.09, 0.5, -13.05 ]
					},
					{ "time": 0.6667, "value": -13.05 }
				],
				"translate": [
					{ "curve": "stepped" },
					{ "time": 0.6667 }
				],
				"scale": [
					{ "curve": "stepped" },
					{ "time": 0.6667 }
				],
				"shear": [
					{ "curve": "stepped" },
					{ "time": 0.6667 }
				]
			},
			"R_foot": {
				"rotate": [
					{
						"value": -51.61,
						"curve": [ 0.056, -51.61, 0.111, -22.22 ]
					},
					{
						"time": 0.1667,
						"value": -22.22,
						"curve": [ 0.333, -22.22, 0.5, -51.61 ]
					},
					{ "time": 0.6667, "value": -51.61 }
				],
				"translate": [
					{ "curve": "stepped" },
					{ "time": 0.6667 }
				],
				"scale": [
					{ "curve": "stepped" },
					{ "time": 0.6667 }
				],
				"shear": [
					{ "curve": "stepped" },
					{ "time": 0.6667 }
				]
			},
			"R_hand": {
				"rotate": [
					{
						"curve": [ 0.056, 0, 0.111, -6.18 ]
					},
					{
						"time": 0.1667,
						"value": -6.18,
						"curve": [ 0.333, -6.18, 0.5, 0 ]
					},
					{ "time": 0.6667 }
				],
				"translate": [
					{ "curve": "stepped" },
					{ "time": 0.6667 }
				],
				"scale": [
					{ "curve": "stepped" },
					{ "time": 0.6667 }
				],
				"shear": [
					{ "curve": "stepped" },
					{ "time": 0.6667 }
				]
			},
			"R_hand2": {
				"rotate": [
					{
						"curve": [ 0.056, 0, 0.111, -6.18 ]
					},
					{
						"time": 0.1667,
						"value": -6.18,
						"curve": [ 0.333, -6.18, 0.5, 0 ]
					},
					{ "time": 0.6667 }
				],
				"translate": [
					{ "curve": "stepped" },
					{ "time": 0.6667 }
				],
				"scale": [
					{ "curve": "stepped" },
					{ "time": 0.6667 }
				],
				"shear": [
					{ "curve": "stepped" },
					{ "time": 0.6667 }
				]
			},
			"R_hand3": {
				"rotate": [
					{
						"curve": [ 0.056, 0, 0.111, -6.18 ]
					},
					{
						"time": 0.1667,
						"value": -6.18,
						"curve": [ 0.333, -6.18, 0.5, 0 ]
					},
					{ "time": 0.6667 }
				],
				"translate": [
					{ "curve": "stepped" },
					{ "time": 0.6667 }
				],
				"scale": [
					{ "curve": "stepped" },
					{ "time": 0.6667 }
				],
				"shear": [
					{ "curve": "stepped" },
					{ "time": 0.6667 }
				]
			},
			"R_hand4": {
				"rotate": [
					{
						"curve": [ 0.056, 0, 0.111, -6.18 ]
					},
					{
						"time": 0.1667,
						"value": -6.18,
						"curve": [ 0.333, -6.18, 0.5, 0 ]
					},
					{ "time": 0.6667 }
				],
				"translate": [
					{ "curve": "stepped" },
					{ "time": 0.6667 }
				],
				"scale": [
					{ "curve": "stepped" },
					{ "time": 0.6667 }
				],
				"shear": [
					{ "curve": "stepped" },
					{ "time": 0.6667 }
				]
			},
			"R_hand5": {
				"rotate": [
					{
						"curve": [ 0.056, 0, 0.111, -6.18 ]
					},
					{
						"time": 0.1667,
						"value": -6.18,
						"curve": [ 0.333, -6.18, 0.5, 0 ]
					},
					{ "time": 0.6667 }
				],
				"translate": [
					{ "curve": "stepped" },
					{ "time": 0.6667 }
				],
				"scale": [
					{ "curve": "stepped" },
					{ "time": 0.6667 }
				],
				"shear": [
					{ "curve": "stepped" },
					{ "time": 0.6667 }
				]
			},
			"R_hand6": {
				"rotate": [
					{
						"curve": [ 0.056, 0, 0.111, -6.18 ]
					},
					{
						"time": 0.1667,
						"value": -6.18,
						"curve": [ 0.333, -6.18, 0.5, 0 ]
					},
					{ "time": 0.6667 }
				],
				"translate": [
					{ "curve": "stepped" },
					{ "time": 0.6667 }
				],
				"scale": [
					{ "curve": "stepped" },
					{ "time": 0.6667 }
				],
				"shear": [
					{ "curve": "stepped" },
					{ "time": 0.6667 }
				]
			},
			"R_hand7": {
				"rotate": [
					{
						"curve": [ 0.056, 0, 0.111, -6.18 ]
					},
					{
						"time": 0.1667,
						"value": -6.18,
						"curve": [ 0.333, -6.18, 0.5, 0 ]
					},
					{ "time": 0.6667 }
				],
				"translate": [
					{ "curve": "stepped" },
					{ "time": 0.6667 }
				],
				"scale": [
					{ "curve": "stepped" },
					{ "time": 0.6667 }
				],
				"shear": [
					{ "curve": "stepped" },
					{ "time": 0.6667 }
				]
			},
			"bady2": {
				"rotate": [
					{
						"curve": [ 0.056, 0, 0.111, 35.77 ]
					},
					{
						"time": 0.1667,
						"value": 35.77,
						"curve": [ 0.222, 35.77, 0.278, -0.37 ]
					},
					{
						"time": 0.3333,
						"value": -0.37,
						"curve": [ 0.444, -0.37, 0.556, 0 ]
					},
					{ "time": 0.6667 }
				],
				"translate": [
					{ "curve": "stepped" },
					{ "time": 0.6667 }
				],
				"scale": [
					{ "curve": "stepped" },
					{ "time": 0.6667 }
				],
				"shear": [
					{ "curve": "stepped" },
					{ "time": 0.6667 }
				]
			}
		}
	},
	"Hit_0": {
		"slots": {
			"face": {
				"attachment": [
					{ "name": "watermelon/face" },
					{ "time": 0.1 },
					{ "time": 0.9, "name": "watermelon/face" },
					{ "time": 1, "name": "watermelon/face" }
				]
			},
			"watermelon/face_1": {
				"attachment": [
					{},
					{ "time": 0.1, "name": "watermelon/face_1" },
					{ "time": 0.9 },
					{ "time": 1 }
				]
			}
		},
		"bones": {
			"face": {
				"rotate": [
					{ "curve": "stepped" },
					{ "time": 1 }
				],
				"translate": [
					{
						"curve": [ 0.034, 0, 0.069, 27.61, 0.034, 0, 0.069, 0 ]
					},
					{
						"time": 0.1,
						"x": 27.61,
						"curve": [ 0.402, 27.61, 0.701, 0, 0.402, 0, 0.701, 0 ]
					},
					{ "time": 1 }
				],
				"scale": [
					{ "curve": "stepped" },
					{ "time": 1 }
				],
				"shear": [
					{ "curve": "stepped" },
					{ "time": 1 }
				]
			},
			"root": {
				"rotate": [
					{ "curve": "stepped" },
					{ "time": 1 }
				],
				"translate": [
					{ "curve": "stepped" },
					{ "time": 1 }
				],
				"scale": [
					{ "curve": "stepped" },
					{ "time": 1 }
				],
				"shear": [
					{ "curve": "stepped" },
					{ "time": 1 }
				]
			},
			"bone": {
				"rotate": [
					{
						"curve": [ 0.034, 0, 0.069, -23.82 ]
					},
					{
						"time": 0.1,
						"value": -23.82,
						"curve": [ 0.402, -23.82, 0.701, 0 ]
					},
					{ "time": 1 }
				],
				"translate": [
					{
						"curve": [ 0.111, 0, 0.222, 130.88, 0.111, 0, 0.222, 0 ]
					},
					{
						"time": 0.3333,
						"x": 130.88,
						"curve": [ 0.444, 130.88, 0.556, 98.63, 0.444, 0, 0.556, 0 ]
					},
					{
						"time": 0.6667,
						"x": 76.81,
						"curve": [ 0.778, 55, 0.889, 0, 0.778, 0, 0.889, 0 ]
					},
					{ "time": 1 }
				],
				"scale": [
					{ "curve": "stepped" },
					{ "time": 1 }
				],
				"shear": [
					{ "curve": "stepped" },
					{ "time": 1 }
				]
			},
			"bady": {
				"rotate": [
					{ "curve": "stepped" },
					{ "time": 1 }
				],
				"translate": [
					{ "curve": "stepped" },
					{ "time": 1 }
				],
				"scale": [
					{
						"curve": [ 0.034, 1, 0.069, 0.849, 0.034, 1, 0.069, 1 ]
					},
					{
						"time": 0.1,
						"x": 0.849,
						"curve": [ 0.402, 0.849, 0.701, 1, 0.402, 1, 0.701, 1 ]
					},
					{ "time": 1 }
				],
				"shear": [
					{ "curve": "stepped" },
					{ "time": 1 }
				]
			},
			"L_foot": {
				"rotate": [
					{
						"curve": [ 0.034, 0, 0.069, -29.08 ]
					},
					{
						"time": 0.1,
						"value": -29.08,
						"curve": [ 0.402, -29.08, 0.701, 0 ]
					},
					{ "time": 1 }
				],
				"translate": [
					{ "curve": "stepped" },
					{ "time": 1 }
				],
				"scale": [
					{ "curve": "stepped" },
					{ "time": 1 }
				],
				"shear": [
					{ "curve": "stepped" },
					{ "time": 1 }
				]
			},
			"L_hand": {
				"rotate": [
					{ "curve": "stepped" },
					{
						"time": 0.0667,
						"curve": [ 0.078, 0, 0.089, 18.3 ]
					},
					{
						"time": 0.1,
						"value": 18.3,
						"curve": [ 0.389, 18.3, 0.711, 0 ]
					},
					{ "time": 1 }
				],
				"translate": [
					{ "curve": "stepped" },
					{ "time": 0.0667, "curve": "stepped" },
					{ "time": 1 }
				],
				"scale": [
					{ "curve": "stepped" },
					{ "time": 0.0667, "curve": "stepped" },
					{ "time": 1 }
				],
				"shear": [
					{ "curve": "stepped" },
					{ "time": 0.0667, "curve": "stepped" },
					{ "time": 1 }
				]
			},
			"R_foot": {
				"rotate": [
					{
						"curve": [ 0.034, 0, 0.069, 41.31 ]
					},
					{
						"time": 0.1,
						"value": 41.31,
						"curve": [ 0.402, 41.31, 0.701, 0 ]
					},
					{ "time": 1 }
				],
				"translate": [
					{ "curve": "stepped" },
					{ "time": 1 }
				],
				"scale": [
					{ "curve": "stepped" },
					{ "time": 1 }
				],
				"shear": [
					{ "curve": "stepped" },
					{ "time": 1 }
				]
			},
			"R_hand": {
				"rotate": [
					{
						"curve": [ 0.033, 0, 0.067, -122.4 ]
					},
					{
						"time": 0.1,
						"value": -122.4,
						"curve": [ 0.4, -122.4, 0.7, 0 ]
					},
					{ "time": 1 }
				],
				"translate": [
					{ "curve": "stepped" },
					{ "time": 1 }
				],
				"scale": [
					{ "curve": "stepped" },
					{ "time": 1 }
				],
				"shear": [
					{ "curve": "stepped" },
					{ "time": 1 }
				]
			},
			"R_hand2": {
				"rotate": [
					{ "curve": "stepped" },
					{ "time": 1 }
				],
				"translate": [
					{ "curve": "stepped" },
					{ "time": 1 }
				],
				"scale": [
					{ "curve": "stepped" },
					{ "time": 1 }
				],
				"shear": [
					{ "curve": "stepped" },
					{ "time": 1 }
				]
			},
			"R_hand3": {
				"rotate": [
					{ "curve": "stepped" },
					{ "time": 1 }
				],
				"translate": [
					{ "curve": "stepped" },
					{ "time": 1 }
				],
				"scale": [
					{ "curve": "stepped" },
					{ "time": 1 }
				],
				"shear": [
					{ "curve": "stepped" },
					{ "time": 1 }
				]
			},
			"R_hand4": {
				"rotate": [
					{ "curve": "stepped" },
					{ "time": 1 }
				],
				"translate": [
					{ "curve": "stepped" },
					{ "time": 1 }
				],
				"scale": [
					{ "curve": "stepped" },
					{ "time": 1 }
				],
				"shear": [
					{ "curve": "stepped" },
					{ "time": 1 }
				]
			},
			"R_hand5": {
				"rotate": [
					{ "curve": "stepped" },
					{ "time": 1 }
				],
				"translate": [
					{ "curve": "stepped" },
					{ "time": 1 }
				],
				"scale": [
					{ "curve": "stepped" },
					{ "time": 1 }
				],
				"shear": [
					{ "curve": "stepped" },
					{ "time": 1 }
				]
			},
			"R_hand6": {
				"rotate": [
					{ "curve": "stepped" },
					{ "time": 1 }
				],
				"translate": [
					{ "curve": "stepped" },
					{ "time": 1 }
				],
				"scale": [
					{ "curve": "stepped" },
					{ "time": 1 }
				],
				"shear": [
					{ "curve": "stepped" },
					{ "time": 1 }
				]
			},
			"R_hand7": {
				"rotate": [
					{ "curve": "stepped" },
					{ "time": 1 }
				],
				"translate": [
					{ "curve": "stepped" },
					{ "time": 1 }
				],
				"scale": [
					{ "curve": "stepped" },
					{ "time": 1 }
				],
				"shear": [
					{ "curve": "stepped" },
					{ "time": 1 }
				]
			},
			"L_hand2": {
				"rotate": [
					{ "curve": "stepped" },
					{
						"time": 0.0667,
						"curve": [ 0.078, 0, 0.089, 18.3 ]
					},
					{
						"time": 0.1,
						"value": 18.3,
						"curve": [ 0.389, 18.3, 0.711, 0 ]
					},
					{ "time": 1 }
				],
				"translate": [
					{ "curve": "stepped" },
					{ "time": 0.0667, "curve": "stepped" },
					{ "time": 1 }
				],
				"scale": [
					{ "curve": "stepped" },
					{ "time": 0.0667, "curve": "stepped" },
					{ "time": 1 }
				],
				"shear": [
					{ "curve": "stepped" },
					{ "time": 0.0667, "curve": "stepped" },
					{ "time": 1 }
				]
			},
			"L_hand3": {
				"rotate": [
					{ "curve": "stepped" },
					{
						"time": 0.0667,
						"curve": [ 0.078, 0, 0.089, 18.3 ]
					},
					{
						"time": 0.1,
						"value": 18.3,
						"curve": [ 0.389, 18.3, 0.711, 0 ]
					},
					{ "time": 1 }
				],
				"translate": [
					{ "curve": "stepped" },
					{ "time": 0.0667, "curve": "stepped" },
					{ "time": 1 }
				],
				"scale": [
					{ "curve": "stepped" },
					{ "time": 0.0667, "curve": "stepped" },
					{ "time": 1 }
				],
				"shear": [
					{ "curve": "stepped" },
					{ "time": 0.0667, "curve": "stepped" },
					{ "time": 1 }
				]
			},
			"L_hand4": {
				"rotate": [
					{ "curve": "stepped" },
					{
						"time": 0.0667,
						"curve": [ 0.078, 0, 0.089, 18.3 ]
					},
					{
						"time": 0.1,
						"value": 18.3,
						"curve": [ 0.389, 18.3, 0.711, 0 ]
					},
					{ "time": 1 }
				],
				"translate": [
					{ "curve": "stepped" },
					{ "time": 0.0667, "curve": "stepped" },
					{ "time": 1 }
				],
				"scale": [
					{ "curve": "stepped" },
					{ "time": 0.0667, "curve": "stepped" },
					{ "time": 1 }
				],
				"shear": [
					{ "curve": "stepped" },
					{ "time": 0.0667, "curve": "stepped" },
					{ "time": 1 }
				]
			},
			"L_hand5": {
				"rotate": [
					{ "curve": "stepped" },
					{
						"time": 0.0667,
						"curve": [ 0.078, 0, 0.089, 18.3 ]
					},
					{
						"time": 0.1,
						"value": 18.3,
						"curve": [ 0.389, 18.3, 0.711, 0 ]
					},
					{ "time": 1 }
				],
				"translate": [
					{ "curve": "stepped" },
					{ "time": 0.0667, "curve": "stepped" },
					{ "time": 1 }
				],
				"scale": [
					{ "curve": "stepped" },
					{ "time": 0.0667, "curve": "stepped" },
					{ "time": 1 }
				],
				"shear": [
					{ "curve": "stepped" },
					{ "time": 0.0667, "curve": "stepped" },
					{ "time": 1 }
				]
			},
			"L_hand6": {
				"rotate": [
					{ "curve": "stepped" },
					{
						"time": 0.0667,
						"curve": [ 0.078, 0, 0.089, 18.3 ]
					},
					{
						"time": 0.1,
						"value": 18.3,
						"curve": [ 0.389, 18.3, 0.711, 0 ]
					},
					{ "time": 1 }
				],
				"translate": [
					{ "curve": "stepped" },
					{ "time": 0.0667, "curve": "stepped" },
					{ "time": 1 }
				],
				"scale": [
					{ "curve": "stepped" },
					{ "time": 0.0667, "curve": "stepped" },
					{ "time": 1 }
				],
				"shear": [
					{ "curve": "stepped" },
					{ "time": 0.0667, "curve": "stepped" },
					{ "time": 1 }
				]
			},
			"L_hand7": {
				"rotate": [
					{ "curve": "stepped" },
					{
						"time": 0.0667,
						"curve": [ 0.078, 0, 0.089, 18.3 ]
					},
					{
						"time": 0.1,
						"value": 18.3,
						"curve": [ 0.389, 18.3, 0.711, 0 ]
					},
					{ "time": 1 }
				],
				"translate": [
					{ "curve": "stepped" },
					{ "time": 0.0667, "curve": "stepped" },
					{ "time": 1 }
				],
				"scale": [
					{ "curve": "stepped" },
					{ "time": 0.0667, "curve": "stepped" },
					{ "time": 1 }
				],
				"shear": [
					{ "curve": "stepped" },
					{ "time": 0.0667, "curve": "stepped" },
					{ "time": 1 }
				]
			},
			"bady2": {
				"rotate": [
					{ "curve": "stepped" },
					{
						"time": 0.0667,
						"curve": [ 0.101, 0, 0.069, 78.3 ]
					},
					{
						"time": 0.1,
						"value": 78.3,
						"curve": [ 0.402, 78.3, 0.701, 0 ]
					},
					{ "time": 1 }
				],
				"translate": [
					{ "curve": "stepped" },
					{ "time": 0.0667, "curve": "stepped" },
					{ "time": 1 }
				],
				"scale": [
					{ "curve": "stepped" },
					{ "time": 0.0667, "curve": "stepped" },
					{ "time": 1 }
				],
				"shear": [
					{ "curve": "stepped" },
					{ "time": 0.0667, "curve": "stepped" },
					{ "time": 1 }
				]
			}
		},
		"drawOrder": [
			{
				"time": 0.1,
				"offsets": [
					{ "slot": "R_hand", "offset": 1 }
				]
			}
		]
	},
	"Hit_1": {
		"slots": {
			"face": {
				"attachment": [
					{}
				]
			},
			"watermelon/face_2": {
				"attachment": [
					{ "name": "watermelon/face_2" }
				]
			}
		},
		"bones": {
			"face": {
				"rotate": [
					{}
				],
				"translate": [
					{},
					{ "time": 0.0667, "x": -11.23, "y": 14.25 }
				],
				"scale": [
					{}
				],
				"shear": [
					{}
				]
			},
			"R_hand": {
				"rotate": [
					{ "value": 20.65 }
				],
				"translate": [
					{}
				],
				"scale": [
					{}
				],
				"shear": [
					{}
				]
			},
			"R_hand2": {
				"rotate": [
					{ "value": 20.65 }
				],
				"translate": [
					{}
				],
				"scale": [
					{}
				],
				"shear": [
					{}
				]
			},
			"R_hand3": {
				"rotate": [
					{ "value": 20.65 }
				],
				"translate": [
					{}
				],
				"scale": [
					{}
				],
				"shear": [
					{}
				]
			},
			"R_hand4": {
				"rotate": [
					{ "value": 20.65 }
				],
				"translate": [
					{}
				],
				"scale": [
					{}
				],
				"shear": [
					{}
				]
			},
			"R_hand5": {
				"rotate": [
					{ "value": 20.65 }
				],
				"translate": [
					{}
				],
				"scale": [
					{}
				],
				"shear": [
					{}
				]
			},
			"R_hand6": {
				"rotate": [
					{ "value": 20.65 }
				],
				"translate": [
					{}
				],
				"scale": [
					{}
				],
				"shear": [
					{}
				]
			},
			"R_hand7": {
				"rotate": [
					{ "value": 20.65 }
				],
				"translate": [
					{}
				],
				"scale": [
					{}
				],
				"shear": [
					{}
				]
			},
			"L_hand3": {
				"rotate": [
					{ "value": 12.36 }
				],
				"translate": [
					{}
				],
				"scale": [
					{}
				],
				"shear": [
					{}
				]
			},
			"L_hand4": {
				"rotate": [
					{ "value": 12.36 }
				],
				"translate": [
					{}
				],
				"scale": [
					{}
				],
				"shear": [
					{}
				]
			},
			"L_hand5": {
				"rotate": [
					{ "value": 12.36 }
				],
				"translate": [
					{}
				],
				"scale": [
					{}
				],
				"shear": [
					{}
				]
			},
			"L_hand6": {
				"rotate": [
					{ "value": 12.36 }
				],
				"translate": [
					{}
				],
				"scale": [
					{}
				],
				"shear": [
					{}
				]
			},
			"L_hand7": {
				"rotate": [
					{ "value": 12.36 }
				],
				"translate": [
					{}
				],
				"scale": [
					{}
				],
				"shear": [
					{}
				]
			},
			"L_hand": {
				"rotate": [
					{ "value": -40.87 }
				],
				"translate": [
					{}
				],
				"scale": [
					{}
				],
				"shear": [
					{}
				]
			},
			"L_foot": {
				"rotate": [
					{ "value": -43.04 }
				],
				"translate": [
					{ "x": -121.03, "y": 43.03 }
				],
				"scale": [
					{}
				],
				"shear": [
					{}
				]
			},
			"R_foot": {
				"rotate": [
					{ "value": 39.83 }
				],
				"translate": [
					{}
				],
				"scale": [
					{}
				],
				"shear": [
					{}
				]
			},
			"bady2": {
				"rotate": [
					{ "value": -31.45 }
				],
				"translate": [
					{}
				],
				"scale": [
					{}
				],
				"shear": [
					{}
				]
			},
			"root": {
				"rotate": [
					{}
				],
				"translate": [
					{}
				],
				"scale": [
					{}
				],
				"shear": [
					{}
				]
			},
			"L_hand2": {
				"rotate": [
					{}
				],
				"translate": [
					{}
				],
				"scale": [
					{}
				],
				"shear": [
					{}
				]
			},
			"bady": {
				"rotate": [
					{}
				],
				"translate": [
					{}
				],
				"scale": [
					{}
				],
				"shear": [
					{}
				]
			},
			"bone": {
				"rotate": [
					{ "value": -23.15 },
					{ "time": 0.0667, "value": -33.86 },
					{ "time": 0.1333, "value": -23.15 }
				],
				"translate": [
					{},
					{ "time": 0.0667, "x": 15.1, "y": -10.13 },
					{ "time": 0.1333 }
				],
				"scale": [
					{ "curve": "stepped" },
					{ "time": 0.0667, "curve": "stepped" },
					{ "time": 0.1333 }
				],
				"shear": [
					{ "curve": "stepped" },
					{ "time": 0.0667, "curve": "stepped" },
					{ "time": 0.1333 }
				]
			}
		},
		"drawOrder": [
			{
				"offsets": [
					{ "slot": "L_foot", "offset": 8 },
					{ "slot": "R_foot", "offset": 8 }
				]
			},
			{
				"time": 0.0667,
				"offsets": [
					{ "slot": "L_foot", "offset": 8 },
					{ "slot": "R_foot", "offset": 8 }
				]
			},
			{
				"time": 0.1333,
				"offsets": [
					{ "slot": "L_foot", "offset": 8 },
					{ "slot": "R_foot", "offset": 8 }
				]
			}
		]
	},
	"Hit_2": {
		"slots": {
			"face": {
				"attachment": [
					{}
				]
			},
			"watermelon/face_2": {
				"attachment": [
					{}
				]
			},
			"watermelon/face_3": {
				"attachment": [
					{ "name": "watermelon/face_3" }
				]
			}
		},
		"bones": {
			"face": {
				"translate": [
					{ "time": 0.0667, "x": -29.08, "y": 15.76 }
				]
			},
			"L_hand": {
				"rotate": [
					{ "value": 42.06 }
				]
			},
			"L_hand2": {
				"rotate": [
					{ "value": 42.06 }
				]
			},
			"L_hand3": {
				"rotate": [
					{ "value": 56.68 }
				]
			},
			"L_hand4": {
				"rotate": [
					{ "value": 47.82 }
				]
			},
			"L_hand5": {
				"rotate": [
					{ "value": 33.05 }
				]
			},
			"L_hand6": {
				"rotate": [
					{ "value": 23.49 }
				]
			},
			"L_hand7": {
				"rotate": [
					{ "value": 23.49 }
				]
			},
			"R_hand4": {
				"rotate": [
					{ "value": -0.56 }
				]
			},
			"R_hand5": {
				"rotate": [
					{ "value": -0.56 }
				]
			},
			"R_hand6": {
				"rotate": [
					{ "value": -0.56 }
				]
			},
			"R_hand7": {
				"rotate": [
					{ "value": -0.56 }
				]
			},
			"R_hand3": {
				"rotate": [
					{ "value": 8.29 }
				]
			},
			"R_hand": {
				"rotate": [
					{ "value": -87.5 }
				]
			},
			"R_hand2": {
				"rotate": [
					{ "value": -18.4 }
				]
			},
			"R_foot": {
				"rotate": [
					{ "value": -96.25 }
				]
			},
			"L_foot": {
				"rotate": [
					{ "value": -9.33 }
				]
			},
			"bady2": {
				"rotate": [
					{ "value": 53.71 }
				]
			},
			"bone": {
				"rotate": [
					{ "value": 21.26 },
					{ "time": 0.0667, "value": 29.21 },
					{ "time": 0.1333, "value": 21.26 }
				],
				"translate": [
					{},
					{ "time": 0.0667, "x": 24.05, "y": 4.01 },
					{ "time": 0.1333 }
				]
			}
		},
		"drawOrder": [
			{
				"offsets": [
					{ "slot": "R_hand", "offset": 5 }
				]
			},
			{
				"time": 0.1333,
				"offsets": [
					{ "slot": "R_hand", "offset": 5 }
				]
			}
		]
	},
	"Hit_3": {
		"slots": {
			"face": {
				"attachment": [
					{}
				]
			},
			"watermelon/face_1": {
				"attachment": [
					{}
				]
			},
			"watermelon/face_2": {
				"attachment": [
					{}
				]
			},
			"watermelon/face_3": {
				"attachment": [
					{}
				]
			},
			"watermelon/face_4": {
				"attachment": [
					{ "name": "watermelon/face_4" }
				]
			}
		},
		"bones": {
			"face": {
				"translate": [
					{ "time": 0.0667, "x": -2.99, "y": 23.49 }
				]
			},
			"R_hand": {
				"rotate": [
					{ "value": 18.43 }
				]
			},
			"R_hand2": {
				"rotate": [
					{ "value": 18.43 }
				]
			},
			"R_hand3": {
				"rotate": [
					{ "value": 18.43 }
				]
			},
			"R_hand4": {
				"rotate": [
					{ "value": 18.43 }
				]
			},
			"R_hand5": {
				"rotate": [
					{ "value": 18.43 }
				]
			},
			"R_hand6": {
				"rotate": [
					{ "value": 18.43 }
				]
			},
			"R_hand7": {
				"rotate": [
					{ "value": 18.43 }
				]
			},
			"bady2": {
				"rotate": [
					{ "value": 25.37 }
				]
			},
			"L_foot": {
				"rotate": [
					{ "value": -53.38 }
				]
			},
			"R_foot": {
				"rotate": [
					{ "value": 37.68 }
				]
			},
			"L_hand": {
				"rotate": [
					{ "value": -95.5 }
				]
			},
			"L_hand2": {
				"rotate": [
					{ "value": 19.74 }
				]
			},
			"L_hand3": {
				"rotate": [
					{ "value": 48.64 }
				]
			},
			"L_hand4": {
				"rotate": [
					{ "value": 18.61 }
				]
			},
			"L_hand5": {
				"rotate": [
					{ "value": 18.61 }
				]
			},
			"L_hand6": {
				"rotate": [
					{ "value": 6.06 }
				]
			},
			"L_hand7": {
				"rotate": [
					{ "value": 6.06 }
				]
			},
			"bone": {
				"rotate": [
					{
						"curve": [ 0.022, 0, 0.044, -4.23 ]
					},
					{
						"time": 0.0667,
						"value": -4.23,
						"curve": [ 0.089, -4.23, 0.111, 0 ]
					},
					{ "time": 0.1333 }
				],
				"translate": [
					{
						"curve": [ 0.022, 0, 0.044, 17.81, 0.022, 0, 0.044, 0 ]
					},
					{
						"time": 0.0667,
						"x": 17.81,
						"curve": [ 0.089, 17.81, 0.111, 0, 0.089, 0, 0.111, 0 ]
					},
					{ "time": 0.1333 }
				]
			}
		}
	},
	"Hit_Fly_1": {
		"slots": {
			"bady": {
				"rgba": [
					{ "time": 0.1667, "color": "ffffffff" },
					{ "time": 0.4667, "color": "ffffff00" }
				]
			},
			"face": {
				"rgba": [
					{ "time": 0.1667, "color": "ffffffff" },
					{ "time": 0.4667, "color": "ffffff00" }
				],
				"attachment": [
					{ "time": 0.0333 }
				]
			},
			"L_foot": {
				"rgba": [
					{ "time": 0.1667, "color": "ffffffff" },
					{ "time": 0.4667, "color": "ffffff00" }
				]
			},
			"L_hand": {
				"rgba": [
					{ "time": 0.1667, "color": "ffffffff" },
					{ "time": 0.4667, "color": "ffffff00" }
				]
			},
			"R_foot": {
				"rgba": [
					{ "time": 0.1667, "color": "ffffffff" },
					{ "time": 0.4667, "color": "ffffff00" }
				]
			},
			"R_hand": {
				"rgba": [
					{ "time": 0.1667, "color": "ffffffff" },
					{ "time": 0.4667, "color": "ffffff00" }
				]
			},
			"watermelon/face_1": {
				"rgba": [
					{ "time": 0.1667, "color": "ffffffff" },
					{ "time": 0.4667, "color": "ffffff00" }
				]
			},
			"watermelon/face_2": {
				"rgba": [
					{ "time": 0.1667, "color": "ffffffff" },
					{ "time": 0.4667, "color": "ffffff00" }
				],
				"attachment": [
					{ "time": 0.0333, "name": "watermelon/face_2" }
				]
			},
			"watermelon/face_3": {
				"rgba": [
					{ "time": 0.1667, "color": "ffffffff" },
					{ "time": 0.4667, "color": "ffffff00" }
				]
			},
			"watermelon/face_4": {
				"rgba": [
					{ "time": 0.1667, "color": "ffffffff" },
					{ "time": 0.4667, "color": "ffffff00" }
				]
			}
		},
		"bones": {
			"face": {
				"rotate": [
					{ "curve": "stepped" },
					{ "time": 0.0333, "curve": "stepped" },
					{ "time": 0.4667 }
				],
				"translate": [
					{ "curve": "stepped" },
					{ "time": 0.0333, "curve": "stepped" },
					{ "time": 0.4667 }
				],
				"scale": [
					{ "curve": "stepped" },
					{ "time": 0.0333, "curve": "stepped" },
					{ "time": 0.4667 }
				],
				"shear": [
					{ "curve": "stepped" },
					{ "time": 0.0333, "curve": "stepped" },
					{ "time": 0.4667 }
				]
			},
			"R_hand": {
				"rotate": [
					{},
					{ "time": 0.0333, "value": 20.65, "curve": "stepped" },
					{ "time": 0.4667, "value": 20.65 }
				],
				"translate": [
					{ "curve": "stepped" },
					{ "time": 0.0333, "curve": "stepped" },
					{ "time": 0.4667 }
				],
				"scale": [
					{ "curve": "stepped" },
					{ "time": 0.0333, "curve": "stepped" },
					{ "time": 0.4667 }
				],
				"shear": [
					{ "curve": "stepped" },
					{ "time": 0.0333, "curve": "stepped" },
					{ "time": 0.4667 }
				]
			},
			"R_hand2": {
				"rotate": [
					{},
					{ "time": 0.0333, "value": 20.65, "curve": "stepped" },
					{ "time": 0.4667, "value": 20.65 }
				],
				"translate": [
					{ "curve": "stepped" },
					{ "time": 0.0333, "curve": "stepped" },
					{ "time": 0.4667 }
				],
				"scale": [
					{ "curve": "stepped" },
					{ "time": 0.0333, "curve": "stepped" },
					{ "time": 0.4667 }
				],
				"shear": [
					{ "curve": "stepped" },
					{ "time": 0.0333, "curve": "stepped" },
					{ "time": 0.4667 }
				]
			},
			"R_hand3": {
				"rotate": [
					{},
					{ "time": 0.0333, "value": 20.65, "curve": "stepped" },
					{ "time": 0.4667, "value": 20.65 }
				],
				"translate": [
					{ "curve": "stepped" },
					{ "time": 0.0333, "curve": "stepped" },
					{ "time": 0.4667 }
				],
				"scale": [
					{ "curve": "stepped" },
					{ "time": 0.0333, "curve": "stepped" },
					{ "time": 0.4667 }
				],
				"shear": [
					{ "curve": "stepped" },
					{ "time": 0.0333, "curve": "stepped" },
					{ "time": 0.4667 }
				]
			},
			"R_hand4": {
				"rotate": [
					{},
					{ "time": 0.0333, "value": 20.65, "curve": "stepped" },
					{ "time": 0.4667, "value": 20.65 }
				],
				"translate": [
					{ "curve": "stepped" },
					{ "time": 0.0333, "curve": "stepped" },
					{ "time": 0.4667 }
				],
				"scale": [
					{ "curve": "stepped" },
					{ "time": 0.0333, "curve": "stepped" },
					{ "time": 0.4667 }
				],
				"shear": [
					{ "curve": "stepped" },
					{ "time": 0.0333, "curve": "stepped" },
					{ "time": 0.4667 }
				]
			},
			"R_hand5": {
				"rotate": [
					{},
					{ "time": 0.0333, "value": 20.65, "curve": "stepped" },
					{ "time": 0.4667, "value": 20.65 }
				],
				"translate": [
					{ "curve": "stepped" },
					{ "time": 0.0333, "curve": "stepped" },
					{ "time": 0.4667 }
				],
				"scale": [
					{ "curve": "stepped" },
					{ "time": 0.0333, "curve": "stepped" },
					{ "time": 0.4667 }
				],
				"shear": [
					{ "curve": "stepped" },
					{ "time": 0.0333, "curve": "stepped" },
					{ "time": 0.4667 }
				]
			},
			"R_hand6": {
				"rotate": [
					{},
					{ "time": 0.0333, "value": 20.65, "curve": "stepped" },
					{ "time": 0.4667, "value": 20.65 }
				],
				"translate": [
					{ "curve": "stepped" },
					{ "time": 0.0333, "curve": "stepped" },
					{ "time": 0.4667 }
				],
				"scale": [
					{ "curve": "stepped" },
					{ "time": 0.0333, "curve": "stepped" },
					{ "time": 0.4667 }
				],
				"shear": [
					{ "curve": "stepped" },
					{ "time": 0.0333, "curve": "stepped" },
					{ "time": 0.4667 }
				]
			},
			"R_hand7": {
				"rotate": [
					{},
					{ "time": 0.0333, "value": 20.65, "curve": "stepped" },
					{ "time": 0.4667, "value": 20.65 }
				],
				"translate": [
					{ "curve": "stepped" },
					{ "time": 0.0333, "curve": "stepped" },
					{ "time": 0.4667 }
				],
				"scale": [
					{ "curve": "stepped" },
					{ "time": 0.0333, "curve": "stepped" },
					{ "time": 0.4667 }
				],
				"shear": [
					{ "curve": "stepped" },
					{ "time": 0.0333, "curve": "stepped" },
					{ "time": 0.4667 }
				]
			},
			"L_hand3": {
				"rotate": [
					{},
					{ "time": 0.0333, "value": 12.36, "curve": "stepped" },
					{ "time": 0.4667, "value": 12.36 }
				],
				"translate": [
					{ "curve": "stepped" },
					{ "time": 0.0333, "curve": "stepped" },
					{ "time": 0.4667 }
				],
				"scale": [
					{ "curve": "stepped" },
					{ "time": 0.0333, "curve": "stepped" },
					{ "time": 0.4667 }
				],
				"shear": [
					{ "curve": "stepped" },
					{ "time": 0.0333, "curve": "stepped" },
					{ "time": 0.4667 }
				]
			},
			"L_hand4": {
				"rotate": [
					{},
					{ "time": 0.0333, "value": 12.36, "curve": "stepped" },
					{ "time": 0.4667, "value": 12.36 }
				],
				"translate": [
					{ "curve": "stepped" },
					{ "time": 0.0333, "curve": "stepped" },
					{ "time": 0.4667 }
				],
				"scale": [
					{ "curve": "stepped" },
					{ "time": 0.0333, "curve": "stepped" },
					{ "time": 0.4667 }
				],
				"shear": [
					{ "curve": "stepped" },
					{ "time": 0.0333, "curve": "stepped" },
					{ "time": 0.4667 }
				]
			},
			"L_hand5": {
				"rotate": [
					{},
					{ "time": 0.0333, "value": 12.36, "curve": "stepped" },
					{ "time": 0.4667, "value": 12.36 }
				],
				"translate": [
					{ "curve": "stepped" },
					{ "time": 0.0333, "curve": "stepped" },
					{ "time": 0.4667 }
				],
				"scale": [
					{ "curve": "stepped" },
					{ "time": 0.0333, "curve": "stepped" },
					{ "time": 0.4667 }
				],
				"shear": [
					{ "curve": "stepped" },
					{ "time": 0.0333, "curve": "stepped" },
					{ "time": 0.4667 }
				]
			},
			"L_hand6": {
				"rotate": [
					{},
					{ "time": 0.0333, "value": 12.36, "curve": "stepped" },
					{ "time": 0.4667, "value": 12.36 }
				],
				"translate": [
					{ "curve": "stepped" },
					{ "time": 0.0333, "curve": "stepped" },
					{ "time": 0.4667 }
				],
				"scale": [
					{ "curve": "stepped" },
					{ "time": 0.0333, "curve": "stepped" },
					{ "time": 0.4667 }
				],
				"shear": [
					{ "curve": "stepped" },
					{ "time": 0.0333, "curve": "stepped" },
					{ "time": 0.4667 }
				]
			},
			"L_hand7": {
				"rotate": [
					{},
					{ "time": 0.0333, "value": 12.36, "curve": "stepped" },
					{ "time": 0.4667, "value": 12.36 }
				],
				"translate": [
					{ "curve": "stepped" },
					{ "time": 0.0333, "curve": "stepped" },
					{ "time": 0.4667 }
				],
				"scale": [
					{ "curve": "stepped" },
					{ "time": 0.0333, "curve": "stepped" },
					{ "time": 0.4667 }
				],
				"shear": [
					{ "curve": "stepped" },
					{ "time": 0.0333, "curve": "stepped" },
					{ "time": 0.4667 }
				]
			},
			"L_hand": {
				"rotate": [
					{},
					{ "time": 0.0333, "value": -40.87, "curve": "stepped" },
					{ "time": 0.4667, "value": -40.87 }
				],
				"translate": [
					{ "curve": "stepped" },
					{ "time": 0.0333, "curve": "stepped" },
					{ "time": 0.4667 }
				],
				"scale": [
					{ "curve": "stepped" },
					{ "time": 0.0333, "curve": "stepped" },
					{ "time": 0.4667 }
				],
				"shear": [
					{ "curve": "stepped" },
					{ "time": 0.0333, "curve": "stepped" },
					{ "time": 0.4667 }
				]
			},
			"L_foot": {
				"rotate": [
					{},
					{ "time": 0.0333, "value": -43.04, "curve": "stepped" },
					{ "time": 0.4667, "value": -43.04 }
				],
				"translate": [
					{},
					{ "time": 0.0333, "x": -121.03, "y": 43.03, "curve": "stepped" },
					{ "time": 0.4667, "x": -121.03, "y": 43.03 }
				],
				"scale": [
					{ "curve": "stepped" },
					{ "time": 0.0333, "curve": "stepped" },
					{ "time": 0.4667 }
				],
				"shear": [
					{ "curve": "stepped" },
					{ "time": 0.0333, "curve": "stepped" },
					{ "time": 0.4667 }
				]
			},
			"R_foot": {
				"rotate": [
					{},
					{ "time": 0.0333, "value": 39.83, "curve": "stepped" },
					{ "time": 0.4667, "value": 39.83 }
				],
				"translate": [
					{ "curve": "stepped" },
					{ "time": 0.0333, "curve": "stepped" },
					{ "time": 0.4667 }
				],
				"scale": [
					{ "curve": "stepped" },
					{ "time": 0.0333, "curve": "stepped" },
					{ "time": 0.4667 }
				],
				"shear": [
					{ "curve": "stepped" },
					{ "time": 0.0333, "curve": "stepped" },
					{ "time": 0.4667 }
				]
			},
			"bady2": {
				"rotate": [
					{},
					{ "time": 0.0333, "value": -31.45, "curve": "stepped" },
					{ "time": 0.4667, "value": -31.45 }
				],
				"translate": [
					{ "curve": "stepped" },
					{ "time": 0.0333, "curve": "stepped" },
					{ "time": 0.4667 }
				],
				"scale": [
					{ "curve": "stepped" },
					{ "time": 0.0333, "curve": "stepped" },
					{ "time": 0.4667 }
				],
				"shear": [
					{ "curve": "stepped" },
					{ "time": 0.0333, "curve": "stepped" },
					{ "time": 0.4667 }
				]
			},
			"root": {
				"rotate": [
					{ "curve": "stepped" },
					{ "time": 0.0333, "curve": "stepped" },
					{ "time": 0.4667 }
				],
				"translate": [
					{ "curve": "stepped" },
					{ "time": 0.0333, "curve": "stepped" },
					{ "time": 0.4667 }
				],
				"scale": [
					{ "curve": "stepped" },
					{ "time": 0.0333, "curve": "stepped" },
					{ "time": 0.4667 }
				],
				"shear": [
					{ "curve": "stepped" },
					{ "time": 0.0333, "curve": "stepped" },
					{ "time": 0.4667 }
				]
			},
			"L_hand2": {
				"rotate": [
					{ "curve": "stepped" },
					{ "time": 0.0333, "curve": "stepped" },
					{ "time": 0.4667 }
				],
				"translate": [
					{ "curve": "stepped" },
					{ "time": 0.0333, "curve": "stepped" },
					{ "time": 0.4667 }
				],
				"scale": [
					{ "curve": "stepped" },
					{ "time": 0.0333, "curve": "stepped" },
					{ "time": 0.4667 }
				],
				"shear": [
					{ "curve": "stepped" },
					{ "time": 0.0333, "curve": "stepped" },
					{ "time": 0.4667 }
				]
			},
			"bady": {
				"rotate": [
					{ "curve": "stepped" },
					{ "time": 0.0333, "curve": "stepped" },
					{ "time": 0.4667 }
				],
				"translate": [
					{ "curve": "stepped" },
					{ "time": 0.0333, "curve": "stepped" },
					{ "time": 0.4667 }
				],
				"scale": [
					{ "curve": "stepped" },
					{ "time": 0.0333, "curve": "stepped" },
					{ "time": 0.4667 }
				],
				"shear": [
					{ "curve": "stepped" },
					{ "time": 0.0333, "curve": "stepped" },
					{ "time": 0.4667 }
				]
			},
			"bone": {
				"rotate": [
					{},
					{ "time": 0.0333, "value": 8.14 },
					{ "time": 0.1667, "value": -41.84 },
					{ "time": 0.4667, "value": -57.25 }
				],
				"translate": [
					{ "curve": "stepped" },
					{ "time": 0.0333 },
					{ "time": 0.1667, "x": 49.54, "y": 167.9 },
					{ "time": 0.4667, "x": 99.09, "y": -134.87 }
				],
				"scale": [
					{ "curve": "stepped" },
					{ "time": 0.0333, "curve": "stepped" },
					{ "time": 0.4667 }
				],
				"shear": [
					{ "curve": "stepped" },
					{ "time": 0.0333, "curve": "stepped" },
					{ "time": 0.4667 }
				]
			}
		},
		"drawOrder": [
			{
				"time": 0.0333,
				"offsets": [
					{ "slot": "L_foot", "offset": 8 },
					{ "slot": "R_foot", "offset": 8 }
				]
			}
		]
	},
	"Idle": {
		"bones": {
			"bady": {
				"rotate": [
					{
						"value": -8.36,
						"curve": [ 0.199, -8.36, 0.404, 3.98 ]
					},
					{
						"time": 0.6,
						"value": 5.82,
						"curve": [ 0.849, 8.11, 1.086, -8.36 ]
					},
					{ "time": 1.3333, "value": -8.36 }
				],
				"translate": [
					{
						"curve": [ 0.148, 0, 0.285, 0, 0.148, 0, 0.285, 15.34 ]
					},
					{
						"time": 0.4333,
						"y": 15.34,
						"curve": [ 0.621, 0, 0.812, 0, 0.621, 15.34, 0.812, -5.66 ]
					},
					{
						"time": 1,
						"y": -5.66,
						"curve": [ 1.109, 0, 1.224, 0, 1.109, -5.66, 1.224, 0 ]
					},
					{ "time": 1.3333 }
				],
				"scale": [
					{},
					{ "time": 0.6, "x": 1.1, "y": 0.9 },
					{ "time": 1.3333 }
				],
				"shear": [
					{ "curve": "stepped" },
					{ "time": 1.3333 }
				]
			},
			"root": {
				"rotate": [
					{ "curve": "stepped" },
					{ "time": 1.3333 }
				],
				"translate": [
					{ "curve": "stepped" },
					{ "time": 1.3333 }
				],
				"scale": [
					{ "curve": "stepped" },
					{ "time": 1.3333 }
				],
				"shear": [
					{ "curve": "stepped" },
					{ "time": 1.3333 }
				]
			},
			"R_hand": {
				"rotate": [
					{
						"curve": [ 0.148, 0, 0.285, 11.98 ]
					},
					{
						"time": 0.4333,
						"value": 11.98,
						"curve": [ 0.621, 11.98, 0.812, -4.22 ]
					},
					{
						"time": 1,
						"value": -4.22,
						"curve": [ 1.109, -4.22, 1.224, 0 ]
					},
					{ "time": 1.3333 }
				],
				"translate": [
					{ "curve": "stepped" },
					{ "time": 1.3333 }
				],
				"scale": [
					{ "curve": "stepped" },
					{ "time": 1.3333 }
				],
				"shear": [
					{ "curve": "stepped" },
					{ "time": 1.3333 }
				]
			},
			"R_hand2": {
				"rotate": [
					{
						"curve": [ 0.148, 0, 0.285, 11.98 ]
					},
					{
						"time": 0.4333,
						"value": 11.98,
						"curve": [ 0.621, 11.98, 0.812, -4.22 ]
					},
					{
						"time": 1,
						"value": -4.22,
						"curve": [ 1.109, -4.22, 1.224, 0 ]
					},
					{ "time": 1.3333 }
				],
				"translate": [
					{ "curve": "stepped" },
					{ "time": 1.3333 }
				],
				"scale": [
					{ "curve": "stepped" },
					{ "time": 1.3333 }
				],
				"shear": [
					{ "curve": "stepped" },
					{ "time": 1.3333 }
				]
			},
			"R_hand3": {
				"rotate": [
					{
						"curve": [ 0.148, 0, 0.285, 11.98 ]
					},
					{
						"time": 0.4333,
						"value": 11.98,
						"curve": [ 0.621, 11.98, 0.812, -4.22 ]
					},
					{
						"time": 1,
						"value": -4.22,
						"curve": [ 1.109, -4.22, 1.224, 0 ]
					},
					{ "time": 1.3333 }
				],
				"translate": [
					{ "curve": "stepped" },
					{ "time": 1.3333 }
				],
				"scale": [
					{ "curve": "stepped" },
					{ "time": 1.3333 }
				],
				"shear": [
					{ "curve": "stepped" },
					{ "time": 1.3333 }
				]
			},
			"R_hand4": {
				"rotate": [
					{
						"curve": [ 0.148, 0, 0.285, 11.98 ]
					},
					{
						"time": 0.4333,
						"value": 11.98,
						"curve": [ 0.621, 11.98, 0.812, -4.22 ]
					},
					{
						"time": 1,
						"value": -4.22,
						"curve": [ 1.109, -4.22, 1.224, 0 ]
					},
					{ "time": 1.3333 }
				],
				"translate": [
					{ "curve": "stepped" },
					{ "time": 1.3333 }
				],
				"scale": [
					{ "curve": "stepped" },
					{ "time": 1.3333 }
				],
				"shear": [
					{ "curve": "stepped" },
					{ "time": 1.3333 }
				]
			},
			"R_hand5": {
				"rotate": [
					{
						"curve": [ 0.148, 0, 0.285, 11.98 ]
					},
					{
						"time": 0.4333,
						"value": 11.98,
						"curve": [ 0.621, 11.98, 0.812, -4.22 ]
					},
					{
						"time": 1,
						"value": -4.22,
						"curve": [ 1.109, -4.22, 1.224, 0 ]
					},
					{ "time": 1.3333 }
				],
				"translate": [
					{ "curve": "stepped" },
					{ "time": 1.3333 }
				],
				"scale": [
					{ "curve": "stepped" },
					{ "time": 1.3333 }
				],
				"shear": [
					{ "curve": "stepped" },
					{ "time": 1.3333 }
				]
			},
			"R_hand6": {
				"rotate": [
					{
						"curve": [ 0.148, 0, 0.285, 11.98 ]
					},
					{
						"time": 0.4333,
						"value": 11.98,
						"curve": [ 0.621, 11.98, 0.812, -4.22 ]
					},
					{
						"time": 1,
						"value": -4.22,
						"curve": [ 1.109, -4.22, 1.224, 0 ]
					},
					{ "time": 1.3333 }
				],
				"translate": [
					{ "curve": "stepped" },
					{ "time": 1.3333 }
				],
				"scale": [
					{ "curve": "stepped" },
					{ "time": 1.3333 }
				],
				"shear": [
					{ "curve": "stepped" },
					{ "time": 1.3333 }
				]
			},
			"R_hand7": {
				"rotate": [
					{
						"curve": [ 0.148, 0, 0.285, 11.98 ]
					},
					{
						"time": 0.4333,
						"value": 11.98,
						"curve": [ 0.621, 11.98, 0.812, -4.22 ]
					},
					{
						"time": 1,
						"value": -4.22,
						"curve": [ 1.109, -4.22, 1.224, 0 ]
					},
					{ "time": 1.3333 }
				],
				"translate": [
					{ "curve": "stepped" },
					{ "time": 1.3333 }
				],
				"scale": [
					{ "curve": "stepped" },
					{ "time": 1.3333 }
				],
				"shear": [
					{ "curve": "stepped" },
					{ "time": 1.3333 }
				]
			},
			"face": {
				"rotate": [
					{
						"curve": [ 0.199, 0, 0.404, 6.67 ]
					},
					{
						"time": 0.6,
						"value": 6.67,
						"curve": [ 0.849, 6.67, 1.087, 0 ]
					},
					{ "time": 1.3333 }
				],
				"translate": [
					{
						"curve": [ 0.148, 0, 0.285, 0, 0.148, 0, 0.285, 4.82 ]
					},
					{
						"time": 0.4333,
						"y": 4.82,
						"curve": [ 0.572, 0, 0.728, 0, 0.572, 4.82, 0.728, -14.97 ]
					},
					{
						"time": 0.8667,
						"y": -14.97,
						"curve": [ 1.025, 0, 1.175, 0, 1.025, -14.97, 1.175, 0 ]
					},
					{ "time": 1.3333 }
				],
				"scale": [
					{ "curve": "stepped" },
					{ "time": 1.3333 }
				],
				"shear": [
					{ "curve": "stepped" },
					{ "time": 1.3333 }
				]
			},
			"L_foot": {
				"rotate": [
					{
						"curve": [ 0.148, 0, 0.285, -28.95 ]
					},
					{
						"time": 0.4333,
						"value": -28.95,
						"curve": [ 0.621, -28.95, 0.812, -10.02 ]
					},
					{
						"time": 1,
						"value": -4.78,
						"curve": [ 1.109, -1.75, 1.224, 0 ]
					},
					{ "time": 1.3333 }
				],
				"translate": [
					{ "curve": "stepped" },
					{ "time": 1.3333 }
				],
				"scale": [
					{ "curve": "stepped" },
					{ "time": 1.3333 }
				],
				"shear": [
					{ "curve": "stepped" },
					{ "time": 1.3333 }
				]
			},
			"L_hand": {
				"rotate": [
					{
						"curve": [ 0.148, 0, 0.285, 43.11 ]
					},
					{
						"time": 0.4333,
						"value": 43.11,
						"curve": [ 0.621, 43.11, 0.812, -13.75 ]
					},
					{
						"time": 1,
						"value": -13.75,
						"curve": [ 1.109, -13.75, 1.224, 0 ]
					},
					{ "time": 1.3333 }
				],
				"translate": [
					{ "curve": "stepped" },
					{ "time": 1.3333 }
				],
				"scale": [
					{ "curve": "stepped" },
					{ "time": 1.3333 }
				],
				"shear": [
					{ "curve": "stepped" },
					{ "time": 1.3333 }
				]
			},
			"R_foot": {
				"rotate": [
					{
						"curve": [ 0.148, 0, 0.285, 29.88 ]
					},
					{
						"time": 0.4333,
						"value": 29.88,
						"curve": [ 0.621, 29.88, 0.812, 5.57 ]
					},
					{
						"time": 1,
						"value": 2.55,
						"curve": [ 1.109, 0.8, 1.224, 0 ]
					},
					{ "time": 1.3333 }
				],
				"translate": [
					{ "curve": "stepped" },
					{ "time": 1.3333 }
				],
				"scale": [
					{ "curve": "stepped" },
					{ "time": 1.3333 }
				],
				"shear": [
					{ "curve": "stepped" },
					{ "time": 1.3333 }
				]
			},
			"L_hand2": {
				"rotate": [
					{
						"curve": [ 0.148, 0, 0.285, -2.84 ]
					},
					{
						"time": 0.4333,
						"value": -2.84,
						"curve": [ 0.73, -2.84, 1.036, 0 ]
					},
					{ "time": 1.3333 }
				],
				"translate": [
					{ "curve": "stepped" },
					{ "time": 1.3333 }
				],
				"scale": [
					{ "curve": "stepped" },
					{ "time": 1.3333 }
				],
				"shear": [
					{ "curve": "stepped" },
					{ "time": 1.3333 }
				]
			},
			"L_hand3": {
				"rotate": [
					{
						"curve": [ 0.148, 0, 0.285, -2.84 ]
					},
					{
						"time": 0.4333,
						"value": -2.84,
						"curve": [ 0.73, -2.84, 1.036, 0 ]
					},
					{ "time": 1.3333 }
				],
				"translate": [
					{ "curve": "stepped" },
					{ "time": 1.3333 }
				],
				"scale": [
					{ "curve": "stepped" },
					{ "time": 1.3333 }
				],
				"shear": [
					{ "curve": "stepped" },
					{ "time": 1.3333 }
				]
			},
			"L_hand4": {
				"rotate": [
					{
						"curve": [ 0.148, 0, 0.285, -2.84 ]
					},
					{
						"time": 0.4333,
						"value": -2.84,
						"curve": [ 0.73, -2.84, 1.036, 0 ]
					},
					{ "time": 1.3333 }
				],
				"translate": [
					{ "curve": "stepped" },
					{ "time": 1.3333 }
				],
				"scale": [
					{ "curve": "stepped" },
					{ "time": 1.3333 }
				],
				"shear": [
					{ "curve": "stepped" },
					{ "time": 1.3333 }
				]
			},
			"L_hand5": {
				"rotate": [
					{
						"curve": [ 0.148, 0, 0.285, -2.84 ]
					},
					{
						"time": 0.4333,
						"value": -2.84,
						"curve": [ 0.73, -2.84, 1.036, 0 ]
					},
					{ "time": 1.3333 }
				],
				"translate": [
					{ "curve": "stepped" },
					{ "time": 1.3333 }
				],
				"scale": [
					{ "curve": "stepped" },
					{ "time": 1.3333 }
				],
				"shear": [
					{ "curve": "stepped" },
					{ "time": 1.3333 }
				]
			},
			"L_hand6": {
				"rotate": [
					{
						"curve": [ 0.148, 0, 0.285, -2.84 ]
					},
					{
						"time": 0.4333,
						"value": -2.84,
						"curve": [ 0.73, -2.84, 1.036, 0 ]
					},
					{ "time": 1.3333 }
				],
				"translate": [
					{ "curve": "stepped" },
					{ "time": 1.3333 }
				],
				"scale": [
					{ "curve": "stepped" },
					{ "time": 1.3333 }
				],
				"shear": [
					{ "curve": "stepped" },
					{ "time": 1.3333 }
				]
			},
			"L_hand7": {
				"rotate": [
					{
						"curve": [ 0.148, 0, 0.285, -2.84 ]
					},
					{
						"time": 0.4333,
						"value": -2.84,
						"curve": [ 0.73, -2.84, 1.036, 0 ]
					},
					{ "time": 1.3333 }
				],
				"translate": [
					{ "curve": "stepped" },
					{ "time": 1.3333 }
				],
				"scale": [
					{ "curve": "stepped" },
					{ "time": 1.3333 }
				],
				"shear": [
					{ "curve": "stepped" },
					{ "time": 1.3333 }
				]
			},
			"bady2": {
				"rotate": [
					{},
					{ "time": 0.6, "value": 24.98 },
					{ "time": 1.3333 }
				],
				"translate": [
					{ "curve": "stepped" },
					{ "time": 1.3333 }
				],
				"scale": [
					{ "curve": "stepped" },
					{ "time": 1.3333 }
				],
				"shear": [
					{ "curve": "stepped" },
					{ "time": 1.3333 }
				]
			}
		}
	}
}
}